[{"id":7621,"slug":"spekko-dahl-kerrie-met-krispie-uie","title":"Spekko dahl-kerrie met krispie uie","date":"2025-11-15T11:51:23","excerpt":"","categories":[308],"tags":[401,330],"featured":null,"hasRecipe":true,"commentCount":0},{"id":7611,"slug":"eenskottel-hoender","title":"Eenskottel-hoender","date":"2025-10-27T21:02:05","excerpt":"","categories":[7,308],"tags":[27,347,330],"featured":null,"hasRecipe":true,"commentCount":0},{"id":7591,"slug":"beste-gisbroodjie-ooit","title":"Beste gisbroodjie ooit","date":"2025-06-03T19:10:29","excerpt":"","categories":[314,5],"tags":[56,399,400],"featured":null,"hasRecipe":true,"commentCount":0},{"id":7573,"slug":"paaseier-lekkerte","title":"Paaseier-lekkerte","date":"2025-04-07T21:54:43","excerpt":"","categories":[5,320],"tags":[398,396,397],"featured":null,"hasRecipe":true,"commentCount":4},{"id":7560,"slug":"anys-ciabatta","title":"Anys-ciabatta","date":"2025-03-25T11:50:19","excerpt":"","categories":[314,5],"tags":[395,56,67],"featured":null,"hasRecipe":true,"commentCount":4},{"id":7532,"slug":"griekse-dolmades","title":"Griekse Dolmades","date":"2024-10-10T22:23:33","excerpt":"","categories":[33,16],"tags":[394,330],"featured":null,"hasRecipe":true,"commentCount":0},{"id":7519,"slug":"meksikaanserys","title":"Meksikaanserys","date":"2024-09-11T08:57:17","excerpt":"","categories":[33,308,321],"tags":[393,347,330],"featured":null,"hasRecipe":true,"commentCount":0},{"id":7502,"slug":"kaas-en-ryswafels-met-avokado-sprietuie-en-creme-fraiche","title":"Kaas- en ryswafels met avokado, sprietuie en crème fraîche","date":"2024-08-23T16:40:24","excerpt":"","categories":[308,311,321,16],"tags":[347,330],"featured":null,"hasRecipe":true,"commentCount":4},{"id":7493,"slug":"hoendersop","title":"Hoendersop","date":"2024-07-04T23:31:07","excerpt":"","categories":[308],"tags":[27,23],"featured":null,"hasRecipe":true,"commentCount":6},{"id":7478,"slug":"lekker-los-frikadelle","title":"Lekker los frikadelle","date":"2024-03-26T19:43:50","excerpt":"","categories":[313,308],"tags":[392,226],"featured":null,"hasRecipe":true,"commentCount":29},{"id":7466,"slug":"rissie-marmelade","title":"Rissie-marmelade","date":"2024-02-25T22:00:33","excerpt":"","categories":[309],"tags":[390,391,389],"featured":null,"hasRecipe":true,"commentCount":4},{"id":7451,"slug":"salted-karamel-kaaskoek","title":"Salted karamel-kaaskoek","date":"2023-12-12T20:32:02","excerpt":"","categories":[8],"tags":[163,388],"featured":null,"hasRecipe":true,"commentCount":26},{"id":7437,"slug":"botternaan","title":"Botternaan","date":"2023-10-29T11:15:05","excerpt":"","categories":[33],"tags":[],"featured":null,"hasRecipe":true,"commentCount":2},{"id":7426,"slug":"haddock-pastei","title":"Haddock-pastei","date":"2023-09-14T17:43:52","excerpt":"","categories":[30],"tags":[387,102],"featured":null,"hasRecipe":true,"commentCount":12},{"id":7349,"slug":"grondboontjiebotterblokkies","title":"Grondboontjiebotterblokkies","date":"2023-01-17T19:55:56","excerpt":"","categories":[8],"tags":[],"featured":null,"hasRecipe":true,"commentCount":11},{"id":7289,"slug":"mikrogolf-appelkooskonfyt","title":"Mikrogolf-appelkooskonfyt","date":"2022-11-12T16:16:00","excerpt":"","categories":[309],"tags":[],"featured":null,"hasRecipe":true,"commentCount":22},{"id":7238,"slug":"pampoenkos","title":"Pampoenkos","date":"2022-07-09T15:20:20","excerpt":"","categories":[312],"tags":[],"featured":null,"hasRecipe":true,"commentCount":14},{"id":7224,"slug":"snoekfrikadelle","title":"Snoekfrikadelle","date":"2022-06-26T20:16:05","excerpt":"","categories":[311,30],"tags":[],"featured":null,"hasRecipe":true,"commentCount":10},{"id":7202,"slug":"tuisgemaakte-sausage-roll","title":"Tuisgemaakte sausage roll","date":"2022-06-04T10:40:09","excerpt":"","categories":[313,308],"tags":[],"featured":null,"hasRecipe":true,"commentCount":16},{"id":7184,"slug":"romerige-hoenderlewertjies","title":"Romerige hoenderlewertjies","date":"2022-05-31T08:42:34","excerpt":"","categories":[7],"tags":[],"featured":null,"hasRecipe":true,"commentCount":0},{"id":7166,"slug":"souskluitjies","title":"Souskluitjies","date":"2022-05-04T23:30:16","excerpt":"","categories":[8],"tags":[],"featured":null,"hasRecipe":true,"commentCount":10},{"id":7160,"slug":"boontjiebredie-2","title":"Boontjiebredie","date":"2022-05-04T23:27:48","excerpt":"","categories":[308,270],"tags":[],"featured":null,"hasRecipe":true,"commentCount":16},{"id":7153,"slug":"ryspoeding","title":"Ryspoeding","date":"2022-04-27T20:21:29","excerpt":"","categories":[8],"tags":[],"featured":null,"hasRecipe":true,"commentCount":0},{"id":7147,"slug":"nachos","title":"Nacho’s","date":"2022-04-27T20:18:08","excerpt":"","categories":[308],"tags":[],"featured":null,"hasRecipe":true,"commentCount":2},{"id":7127,"slug":"geposjeerde-pere-en-vanieljeroomys","title":"Geposjeerde pere en vanieljeroomys","date":"2022-04-20T17:59:13","excerpt":"","categories":[8],"tags":[376],"featured":null,"hasRecipe":true,"commentCount":8},{"id":7120,"slug":"diepgebraaide-vis-en-tjips","title":"Diepgebraaide vis en tjips","date":"2022-04-20T17:19:24","excerpt":"","categories":[308,30],"tags":[],"featured":null,"hasRecipe":true,"commentCount":8},{"id":7114,"slug":"sjokoladebondeltjies-en-vrugte-yskasblokkies","title":"Sjokoladebondeltjies en Vrugte-yskasblokkies","date":"2022-04-13T20:30:00","excerpt":"","categories":[8],"tags":[375],"featured":null,"hasRecipe":true,"commentCount":6},{"id":7096,"slug":"suurlemoenmeringuetert","title":"Suurlemoenmeringuetert","date":"2022-04-06T12:01:00","excerpt":"","categories":[5,319],"tags":[94],"featured":null,"hasRecipe":true,"commentCount":0},{"id":7088,"slug":"kool-lensiefrikkadelle","title":"Kool-lensiefrikkadelle","date":"2022-04-06T11:55:00","excerpt":"","categories":[308],"tags":[194],"featured":null,"hasRecipe":true,"commentCount":6},{"id":7084,"slug":"nutella-broodpoeding","title":"Nutella broodpoeding","date":"2022-03-30T11:45:21","excerpt":"","categories":[8],"tags":[334],"featured":null,"hasRecipe":true,"commentCount":4},{"id":7078,"slug":"bobotie-met-n-appelkrummellaag","title":"Bobotie met ‘n appelkrummellaag","date":"2022-03-30T11:42:56","excerpt":"","categories":[308,312],"tags":[143],"featured":null,"hasRecipe":true,"commentCount":8},{"id":7064,"slug":"suurlemoenposset","title":"Suurlemoenposset","date":"2022-03-23T14:59:28","excerpt":"","categories":[8],"tags":[24],"featured":null,"hasRecipe":true,"commentCount":2},{"id":7057,"slug":"hoender-breyani","title":"Hoender-breyani","date":"2022-03-23T14:56:03","excerpt":"","categories":[7,308],"tags":[374,27],"featured":null,"hasRecipe":true,"commentCount":6},{"id":7020,"slug":"roomys","title":"Roomys","date":"2022-03-17T20:21:25","excerpt":"","categories":[8],"tags":[345],"featured":null,"hasRecipe":true,"commentCount":7},{"id":7016,"slug":"aartappelslaai","title":"Aartappelslaai","date":"2022-03-17T20:18:25","excerpt":"","categories":[33,12],"tags":[177],"featured":null,"hasRecipe":true,"commentCount":10},{"id":7008,"slug":"lamsribbetjie-in-die-oond","title":"Lamsribbetjie in die oond","date":"2022-03-17T20:14:12","excerpt":"","categories":[308,270],"tags":[120,371],"featured":null,"hasRecipe":true,"commentCount":2},{"id":7000,"slug":"vaalafval","title":"Vaalafval","date":"2022-03-10T14:45:21","excerpt":"","categories":[308],"tags":[129],"featured":null,"hasRecipe":true,"commentCount":4},{"id":6992,"slug":"sneeupoeding","title":"Sneeupoeding","date":"2022-03-10T14:41:38","excerpt":"","categories":[8],"tags":[370],"featured":null,"hasRecipe":true,"commentCount":1},{"id":6977,"slug":"konfyttert-met-belee-cheddarkaas","title":"Konfyttert met beleë cheddarkaas","date":"2022-03-04T09:17:11","excerpt":"","categories":[1],"tags":[369,368],"featured":null,"hasRecipe":true,"commentCount":0},{"id":7052,"slug":"pot-roast","title":"Pot roast","date":"2022-03-02T15:30:00","excerpt":"","categories":[308,11],"tags":[373],"featured":null,"hasRecipe":true,"commentCount":0},{"id":7046,"slug":"pynappelpoeding","title":"Pynappelpoeding","date":"2022-02-23T15:21:00","excerpt":"","categories":[1],"tags":[372],"featured":null,"hasRecipe":true,"commentCount":0},{"id":7042,"slug":"peppermint-crips-tert","title":"Peppermint Crips-tert","date":"2022-02-16T15:19:00","excerpt":"","categories":[8],"tags":[94],"featured":null,"hasRecipe":true,"commentCount":0},{"id":7038,"slug":"roomkaas-met-pekaneute-en-heuning","title":"Roomkaas met pekaneute en heuning","date":"2022-02-16T15:15:00","excerpt":"","categories":[311,16],"tags":[355],"featured":null,"hasRecipe":true,"commentCount":2},{"id":7031,"slug":"bokmelkkaasrolletjie","title":"Bokmelkkaasrolletjie","date":"2022-02-16T15:09:00","excerpt":"","categories":[311,16],"tags":[355],"featured":null,"hasRecipe":true,"commentCount":0},{"id":6962,"slug":"elsabe-daneel-se-tamatiebredie","title":"Elsabé Daneel se Tamatiebredie","date":"2022-02-03T20:40:47","excerpt":"","categories":[308,270],"tags":[368,367],"featured":null,"hasRecipe":true,"commentCount":0},{"id":6423,"slug":"krummel-piesangmuffins","title":"Krummel-piesangmuffins","date":"2022-01-23T10:17:38","excerpt":"","categories":[5],"tags":[326,323,324],"featured":null,"hasRecipe":true,"commentCount":0},{"id":6417,"slug":"2-bestanddeel-sjokoladebrood","title":"Twee-bestanddeel Sjokoladebrood","date":"2022-01-19T18:35:32","excerpt":"","categories":[314,5,8],"tags":[326,233],"featured":null,"hasRecipe":true,"commentCount":6},{"id":6365,"slug":"lemoen-stroopkoek","title":"Lemoen stroopkoek met Cointreau Naartjies","date":"2021-10-17T08:48:42","excerpt":"","categories":[5,316],"tags":[325],"featured":null,"hasRecipe":true,"commentCount":2},{"id":6345,"slug":"nartjie-stroopkoek","title":"Naartjie Stroopkoek","date":"2021-09-20T16:18:34","excerpt":"","categories":[5,316],"tags":[328],"featured":null,"hasRecipe":true,"commentCount":2},{"id":6330,"slug":"lamsrak-met-n-senqu-river-pistachio-krummelkors","title":"Lamsrak met ‘n Senqu River Pistachio-krummelkors","date":"2021-09-10T11:32:31","excerpt":"","categories":[308,270],"tags":[120],"featured":null,"hasRecipe":true,"commentCount":0},{"id":6305,"slug":"sjokolade-cremora-marshmellow-tert-vir-joanita","title":"Sjokolade-cremora-marshmallow-tert vir Joanita","date":"2021-08-14T09:11:28","excerpt":"","categories":[8,319],"tags":[329],"featured":null,"hasRecipe":true,"commentCount":8},{"id":6281,"slug":"sjokoladekoek-ryk-nat-en-verskriklik-lekker","title":"Sjokoladekoek – ryk, nat en verskriklik lekker","date":"2021-08-05T14:32:20","excerpt":"","categories":[5,316],"tags":[],"featured":null,"hasRecipe":true,"commentCount":0},{"id":6266,"slug":"wonderlikste-wortelkoek","title":"Wonderlikste Wortelkoek","date":"2021-07-23T11:52:22","excerpt":"","categories":[5,316],"tags":[],"featured":null,"hasRecipe":true,"commentCount":0},{"id":6254,"slug":"oats-en-piesang-muffins","title":"Oats-en-piesangmuffins","date":"2021-07-21T13:35:26","excerpt":"","categories":[5],"tags":[],"featured":null,"hasRecipe":true,"commentCount":0},{"id":6240,"slug":"melksjokolade-fudge","title":"Melksjokolade Fudge","date":"2021-07-03T10:27:04","excerpt":"","categories":[8],"tags":[],"featured":null,"hasRecipe":false,"commentCount":0},{"id":6232,"slug":"kondensmelk-melkkos","title":"Kondensmelk-melkkos","date":"2021-06-28T11:12:04","excerpt":"","categories":[8],"tags":[],"featured":null,"hasRecipe":false,"commentCount":0},{"id":6210,"slug":"varkrib-wat-kleef-en-blink","title":"Varkrib wat kleef en blink","date":"2021-05-13T08:36:12","excerpt":"","categories":[14],"tags":[292],"featured":null,"hasRecipe":false,"commentCount":0},{"id":6197,"slug":"melkbroodjie","title":"Melkbroodjie","date":"2021-04-19T16:40:52","excerpt":"","categories":[314,5],"tags":[],"featured":null,"hasRecipe":false,"commentCount":0},{"id":6141,"slug":"tiramisu","title":"Tiramisu","date":"2021-01-02T15:49:06","excerpt":"","categories":[8],"tags":[],"featured":null,"hasRecipe":false,"commentCount":0},{"id":6118,"slug":"appelkoosblatjang","title":"Appelkoosblatjang","date":"2020-12-14T14:27:07","excerpt":"","categories":[33],"tags":[],"featured":null,"hasRecipe":false,"commentCount":0},{"id":6068,"slug":"sjokolade-brownies","title":"Sjokolade Brownies","date":"2020-10-04T09:19:57","excerpt":"","categories":[5,8],"tags":[],"featured":null,"hasRecipe":false,"commentCount":0},{"id":6055,"slug":"banoffee-trifles","title":"Banoffee Trifles","date":"2020-08-23T12:02:14","excerpt":"","categories":[5,8],"tags":[],"featured":null,"hasRecipe":false,"commentCount":0},{"id":6051,"slug":"malvalekkertert","title":"Malvalekkertert","date":"2020-08-23T11:59:17","excerpt":"","categories":[5,8],"tags":[],"featured":null,"hasRecipe":false,"commentCount":0},{"id":6048,"slug":"sjokolademousse-kaaskoek","title":"Sjokolademousse-kaaskoek","date":"2020-08-23T11:56:46","excerpt":"","categories":[366,5,8],"tags":[],"featured":null,"hasRecipe":true,"commentCount":0},{"id":6044,"slug":"suurlemoensmeer-pavlova","title":"Suurlemoensmeer-Pavlova","date":"2020-08-17T13:10:18","excerpt":"","categories":[8],"tags":[],"featured":null,"hasRecipe":false,"commentCount":0},{"id":6041,"slug":"groenslaai-met-jougurtsous","title":"Groenslaai met Jougurtsous","date":"2020-08-17T13:07:47","excerpt":"","categories":[12],"tags":[],"featured":null,"hasRecipe":false,"commentCount":0},{"id":6038,"slug":"haddock-gebak","title":"Haddock Gebak","date":"2020-08-17T13:05:26","excerpt":"","categories":[30],"tags":[],"featured":null,"hasRecipe":false,"commentCount":0},{"id":6032,"slug":"koljander-blomkoolrys","title":"Koljander-blomkoolrys","date":"2020-08-12T10:55:08","excerpt":"","categories":[6],"tags":[],"featured":null,"hasRecipe":false,"commentCount":0},{"id":6029,"slug":"grootword-appeltert","title":"Grootword-appeltert","date":"2020-08-12T10:52:49","excerpt":"","categories":[366,5,8],"tags":[],"featured":null,"hasRecipe":true,"commentCount":0},{"id":6026,"slug":"lamskerrie","title":"Lamskerrie","date":"2020-08-12T10:50:30","excerpt":"","categories":[366,11],"tags":[],"featured":null,"hasRecipe":true,"commentCount":0},{"id":6016,"slug":"komkommerblokkieslaai","title":"Komkommerblokkieslaai","date":"2020-08-05T14:08:03","excerpt":"","categories":[12],"tags":[],"featured":null,"hasRecipe":false,"commentCount":0},{"id":6013,"slug":"sinkplaataartappels","title":"Sinkplaataartappels","date":"2020-08-05T14:04:54","excerpt":"","categories":[6],"tags":[],"featured":null,"hasRecipe":false,"commentCount":0},{"id":6010,"slug":"krummeltjops","title":"Krummeltjops","date":"2020-08-05T14:02:05","excerpt":"","categories":[270],"tags":[],"featured":null,"hasRecipe":false,"commentCount":0},{"id":6002,"slug":"blitsige-sjokolademousse","title":"Blitsige sjokolademousse","date":"2020-07-29T16:14:15","excerpt":"","categories":[8],"tags":[],"featured":null,"hasRecipe":false,"commentCount":0},{"id":5999,"slug":"peer-en-bloukaasslaai","title":"Peer-en bloukaasslaai","date":"2020-07-29T16:12:03","excerpt":"","categories":[12],"tags":[],"featured":null,"hasRecipe":false,"commentCount":0},{"id":5996,"slug":"warm-italiaanse-sous","title":"Warm Italiaanse Sous","date":"2020-07-29T16:09:46","excerpt":"","categories":[33],"tags":[],"featured":null,"hasRecipe":false,"commentCount":0},{"id":5994,"slug":"worspaai","title":"Worspaai","date":"2020-07-29T16:06:37","excerpt":"","categories":[11],"tags":[],"featured":null,"hasRecipe":true,"commentCount":0},{"id":5985,"slug":"aartappel-en-preisop","title":"Aartappel en Preisop","date":"2020-07-21T10:07:08","excerpt":"","categories":[16],"tags":[],"featured":null,"hasRecipe":false,"commentCount":0},{"id":5981,"slug":"anna-se-gemmerpoeding","title":"Anna se Gemmerpoeding","date":"2020-07-21T10:03:07","excerpt":"","categories":[8],"tags":[],"featured":null,"hasRecipe":false,"commentCount":0},{"id":5978,"slug":"5978-2","title":"Paula se seekosring","date":"2020-07-21T09:58:56","excerpt":"","categories":[30],"tags":[],"featured":null,"hasRecipe":false,"commentCount":0},{"id":5970,"slug":"sambal","title":"Sambal","date":"2020-07-15T14:30:35","excerpt":"","categories":[33],"tags":[],"featured":null,"hasRecipe":false,"commentCount":0},{"id":5967,"slug":"5967-2","title":"Jogurtbroodjie","date":"2020-07-15T14:28:15","excerpt":"","categories":[5],"tags":[],"featured":null,"hasRecipe":false,"commentCount":0},{"id":6650,"slug":"kerrie-en-piesang-frikkies","title":"Kerrie-en-piesang-frikkies","date":"2020-07-15T14:18:00","excerpt":"","categories":[308,1],"tags":[194],"featured":null,"hasRecipe":true,"commentCount":4},{"id":5957,"slug":"my-ma-se-bobotie","title":"My Ma se Bobotie","date":"2020-07-06T12:00:21","excerpt":"","categories":[11],"tags":[],"featured":null,"hasRecipe":true,"commentCount":10},{"id":5954,"slug":"vinnige-blatjang","title":"Vinnige Blatjang","date":"2020-07-06T11:49:17","excerpt":"","categories":[33],"tags":[],"featured":null,"hasRecipe":false,"commentCount":0},{"id":5951,"slug":"koeksisters-2-bestanddele","title":"Koeksisters – 2 bestanddele","date":"2020-07-06T11:45:52","excerpt":"","categories":[5],"tags":[],"featured":null,"hasRecipe":false,"commentCount":0},{"id":5936,"slug":"klapperrys-2","title":"Klapperrys","date":"2020-06-27T18:33:37","excerpt":"","categories":[33],"tags":[],"featured":null,"hasRecipe":false,"commentCount":0},{"id":5929,"slug":"groen-seekoskerrie","title":"Groen Seekoskerrie","date":"2020-06-27T18:30:32","excerpt":"","categories":[30],"tags":[],"featured":null,"hasRecipe":false,"commentCount":0},{"id":5922,"slug":"thaise-slaaisous","title":"Thaise Slaaisous","date":"2020-06-27T18:25:42","excerpt":"","categories":[33,12],"tags":[],"featured":null,"hasRecipe":false,"commentCount":0},{"id":5913,"slug":"honeycomb","title":"Honeycomb","date":"2020-06-24T16:52:08","excerpt":"","categories":[8],"tags":[291],"featured":null,"hasRecipe":false,"commentCount":0},{"id":5911,"slug":"roly-poly","title":"Roly Poly","date":"2020-06-24T16:50:16","excerpt":"","categories":[8],"tags":[290],"featured":null,"hasRecipe":false,"commentCount":0},{"id":5909,"slug":"bees-dekrib","title":"Bees dekrib","date":"2020-06-24T16:48:43","excerpt":"","categories":[11],"tags":[289],"featured":null,"hasRecipe":false,"commentCount":0},{"id":5903,"slug":"3-bestanddele-kondensmelkroomys","title":"3 Bestanddele Kondensmelkroomys","date":"2020-06-24T16:45:52","excerpt":"","categories":[8],"tags":[288],"featured":null,"hasRecipe":false,"commentCount":0},{"id":5901,"slug":"neuterige-groenbone","title":"Neuterige Groenbone","date":"2020-06-17T14:11:55","excerpt":"","categories":[6],"tags":[],"featured":null,"hasRecipe":false,"commentCount":0},{"id":5894,"slug":"couscous-met-kruie-en-bosbessies","title":"Couscous met kruie en bosbessies","date":"2020-06-17T14:09:50","excerpt":"","categories":[33],"tags":[],"featured":null,"hasRecipe":false,"commentCount":0},{"id":5890,"slug":"rafelvark-pulled-pork","title":"Rafelvark/Pulled Pork","date":"2020-06-17T14:02:13","excerpt":"","categories":[14],"tags":[],"featured":null,"hasRecipe":false,"commentCount":0},{"id":5883,"slug":"koffie-en-sjokolade-trifle","title":"Koffie en Sjokolade Trifle","date":"2020-06-10T11:32:31","excerpt":"","categories":[8],"tags":[],"featured":null,"hasRecipe":false,"commentCount":0},{"id":5881,"slug":"bruinhoender","title":"Bruinhoender","date":"2020-06-10T11:30:25","excerpt":"","categories":[7],"tags":[],"featured":null,"hasRecipe":false,"commentCount":0},{"id":5874,"slug":"koringslaai","title":"Koringslaai","date":"2020-06-10T11:27:47","excerpt":"","categories":[6],"tags":[],"featured":null,"hasRecipe":false,"commentCount":0},{"id":5867,"slug":"plomp-pampoenpoffertjies","title":"Plomp Pampoenpoffertjies","date":"2020-06-03T13:23:48","excerpt":"","categories":[6],"tags":[],"featured":null,"hasRecipe":false,"commentCount":0},{"id":5865,"slug":"kerrie-hoendernekkies","title":"Kerrie honedernekkies","date":"2020-06-03T13:21:08","excerpt":"","categories":[7],"tags":[],"featured":null,"hasRecipe":false,"commentCount":0},{"id":5859,"slug":"stamp-en-stoot","title":"Stamp en Stoot","date":"2020-06-03T13:17:02","excerpt":"","categories":[33],"tags":[],"featured":null,"hasRecipe":false,"commentCount":0},{"id":5841,"slug":"ingelegde-koejawels","title":"Ingelegde Koejawels","date":"2020-05-17T19:27:08","excerpt":"","categories":[8],"tags":[],"featured":null,"hasRecipe":false,"commentCount":0},{"id":5836,"slug":"sjokolade-mousse-kaaskoek","title":"Sjokolade-Mousse-Kaaskoek","date":"2020-05-15T13:37:40","excerpt":"","categories":[8],"tags":[],"featured":null,"hasRecipe":false,"commentCount":0},{"id":5829,"slug":"souttert","title":"Souttert","date":"2020-05-12T13:57:39","excerpt":"","categories":[5],"tags":[],"featured":null,"hasRecipe":false,"commentCount":0},{"id":5811,"slug":"lemoenbroodjie","title":"Lemoenbroodjie","date":"2020-05-01T16:11:43","excerpt":"","categories":[314,5],"tags":[],"featured":null,"hasRecipe":false,"commentCount":0},{"id":5801,"slug":"vetkoek","title":"Vetkoek","date":"2020-04-25T14:46:57","excerpt":"","categories":[5],"tags":[],"featured":null,"hasRecipe":false,"commentCount":0},{"id":5794,"slug":"bruinbrood","title":"Bruinbrood","date":"2020-04-21T14:51:38","excerpt":"","categories":[314,5],"tags":[],"featured":null,"hasRecipe":false,"commentCount":0},{"id":5790,"slug":"naan","title":"Naan","date":"2020-04-21T14:24:09","excerpt":"","categories":[5],"tags":[],"featured":null,"hasRecipe":false,"commentCount":0},{"id":5787,"slug":"sousboontjies","title":"Sousboontjies","date":"2020-04-21T14:11:00","excerpt":"","categories":[12],"tags":[],"featured":null,"hasRecipe":false,"commentCount":0},{"id":5777,"slug":"lemon-curd-suurlemoensmeer","title":"Lemon Curd / Suurlemoensmeer","date":"2020-04-21T13:35:30","excerpt":"","categories":[8],"tags":[],"featured":null,"hasRecipe":false,"commentCount":0},{"id":5725,"slug":"sjokoladekoek","title":"Sjokoladekoek","date":"2020-04-21T12:28:40","excerpt":"","categories":[5],"tags":[],"featured":null,"hasRecipe":false,"commentCount":0},{"id":5711,"slug":"mosterdsous","title":"Mosterdsous","date":"2019-10-21T12:01:08","excerpt":"","categories":[33],"tags":[287],"featured":null,"hasRecipe":false,"commentCount":0},{"id":5702,"slug":"spekko-kerrie-en-rys-frikkadelle","title":"Spekko kerrie-en-rys-frikadelle","date":"2019-10-11T12:16:30","excerpt":"","categories":[308],"tags":[194,330],"featured":null,"hasRecipe":false,"commentCount":0},{"id":5698,"slug":"3-bestanddele-peanutbutter-koekies","title":"3 Bestanddele peanut butter-koekies","date":"2019-10-11T12:13:25","excerpt":"","categories":[5,317],"tags":[282,331,280],"featured":null,"hasRecipe":false,"commentCount":0},{"id":5695,"slug":"piesangmuffins","title":"Piesangmuffins","date":"2019-10-01T09:11:33","excerpt":"","categories":[5],"tags":[279],"featured":null,"hasRecipe":false,"commentCount":0},{"id":5692,"slug":"3-bestanddele-krismiskoek","title":"3 Bestanddele Krismiskoek","date":"2019-10-01T09:07:56","excerpt":"","categories":[5],"tags":[277,278],"featured":null,"hasRecipe":false,"commentCount":0},{"id":5688,"slug":"slapdeeg-vinnige-kaasskons","title":"Slapdeeg vinnige kaasskons","date":"2019-09-09T13:31:09","excerpt":"","categories":[5],"tags":[276],"featured":null,"hasRecipe":false,"commentCount":0},{"id":5678,"slug":"kondensmelktert","title":"Kondensmelktert","date":"2019-08-07T17:19:58","excerpt":"","categories":[8],"tags":[275],"featured":null,"hasRecipe":false,"commentCount":0},{"id":5675,"slug":"kerrievis","title":"Kerrievis","date":"2019-08-07T17:17:57","excerpt":"","categories":[30],"tags":[274],"featured":null,"hasRecipe":false,"commentCount":0},{"id":5672,"slug":"snoektertjies","title":"Snoektertjies","date":"2019-08-07T17:15:42","excerpt":"","categories":[30],"tags":[273],"featured":null,"hasRecipe":false,"commentCount":0},{"id":5666,"slug":"sjokoladepoeding-2","title":"Sjokoladepoeding","date":"2019-07-31T17:19:04","excerpt":"","categories":[8],"tags":[272],"featured":null,"hasRecipe":false,"commentCount":0},{"id":5663,"slug":"skaapstertjies","title":"Skaapstertjies","date":"2019-07-31T17:17:05","excerpt":"","categories":[270],"tags":[271],"featured":null,"hasRecipe":false,"commentCount":0},{"id":5660,"slug":"gevulde-tamaties","title":"Gevulde Tamaties","date":"2019-07-31T17:15:54","excerpt":"","categories":[33],"tags":[269],"featured":null,"hasRecipe":false,"commentCount":0},{"id":5648,"slug":"baklava","title":"Baklava","date":"2019-07-24T17:19:51","excerpt":"","categories":[8],"tags":[268],"featured":null,"hasRecipe":false,"commentCount":0},{"id":5645,"slug":"hoenderlekkerte","title":"Hoenderlekkerte","date":"2019-07-24T17:17:44","excerpt":"","categories":[7],"tags":[267],"featured":null,"hasRecipe":false,"commentCount":0},{"id":5642,"slug":"spanakopita","title":"Spanakopita","date":"2019-07-24T17:15:40","excerpt":"","categories":[16],"tags":[266],"featured":null,"hasRecipe":false,"commentCount":0},{"id":5639,"slug":"maklike-trifle","title":"Maklike Trifle","date":"2019-07-17T17:17:34","excerpt":"","categories":[8],"tags":[265],"featured":null,"hasRecipe":false,"commentCount":0},{"id":5636,"slug":"soetpatats","title":"Soetpatats","date":"2019-07-17T17:16:02","excerpt":"","categories":[33,6],"tags":[264,263],"featured":null,"hasRecipe":false,"commentCount":0},{"id":5633,"slug":"soet-suur-blomkoolkerrie","title":"Soet-suur Blomkoolkerrie","date":"2019-07-17T17:15:30","excerpt":"","categories":[6],"tags":[262,261,131,260],"featured":null,"hasRecipe":false,"commentCount":0},{"id":5629,"slug":"wortelsambal","title":"Wortelsambal","date":"2019-07-11T14:20:30","excerpt":"","categories":[33],"tags":[259],"featured":null,"hasRecipe":false,"commentCount":0},{"id":5622,"slug":"klapperrys","title":"Klapperrys","date":"2019-07-10T17:28:26","excerpt":"","categories":[33],"tags":[257],"featured":null,"hasRecipe":false,"commentCount":0},{"id":5626,"slug":"tamatiesambal","title":"Tamatiesambal","date":"2019-07-10T17:17:16","excerpt":"","categories":[33],"tags":[258],"featured":null,"hasRecipe":false,"commentCount":0},{"id":5619,"slug":"botterhoender","title":"Botterhoender","date":"2019-07-10T17:15:39","excerpt":"","categories":[7],"tags":[256,27],"featured":null,"hasRecipe":false,"commentCount":0},{"id":5616,"slug":"piesangroomys","title":"Piesangroomys","date":"2019-07-03T17:18:18","excerpt":"","categories":[8],"tags":[255],"featured":null,"hasRecipe":false,"commentCount":0},{"id":5613,"slug":"ma-se-skaapboud","title":"Ma se Skaapboud","date":"2019-07-03T17:17:22","excerpt":"","categories":[308,270],"tags":[254,78],"featured":null,"hasRecipe":false,"commentCount":0},{"id":5611,"slug":"kruisementertjies","title":"Kruisementertjies","date":"2019-07-03T17:16:24","excerpt":"","categories":[33,6],"tags":[253,252],"featured":null,"hasRecipe":false,"commentCount":0},{"id":5605,"slug":"soetwortels-met-byt","title":"Soetwortels-met-byt","date":"2019-07-03T17:15:46","excerpt":"","categories":[33,6],"tags":[251,250],"featured":null,"hasRecipe":false,"commentCount":0},{"id":5591,"slug":"pruim-clafoutis","title":"Pruim-clafoutis","date":"2019-06-26T17:17:18","excerpt":"","categories":[8],"tags":[249],"featured":null,"hasRecipe":false,"commentCount":0},{"id":5589,"slug":"jambalaya","title":"Jambalaya","date":"2019-06-26T17:16:03","excerpt":"","categories":[7],"tags":[248],"featured":null,"hasRecipe":false,"commentCount":0},{"id":5584,"slug":"alles-in-een-ontbyt","title":"Alles-In-Een-Ontbyt","date":"2019-06-26T17:15:27","excerpt":"","categories":[332],"tags":[246,247],"featured":null,"hasRecipe":false,"commentCount":0},{"id":5572,"slug":"boontjiebredie","title":"Boontjiebredie","date":"2019-06-19T17:15:46","excerpt":"","categories":[6],"tags":[243,241,242],"featured":null,"hasRecipe":false,"commentCount":0},{"id":5580,"slug":"malvapoeding","title":"Malvapoeding","date":"2019-06-19T17:15:16","excerpt":"","categories":[5,8],"tags":[245,167],"featured":null,"hasRecipe":true,"commentCount":0},{"id":5577,"slug":"pampoenmoes","title":"Pampoenmoes","date":"2019-06-19T17:15:06","excerpt":"","categories":[6],"tags":[180,244],"featured":null,"hasRecipe":false,"commentCount":0},{"id":5569,"slug":"rosti","title":"Rösti","date":"2019-06-12T17:15:53","excerpt":"","categories":[33],"tags":[240,177,239],"featured":null,"hasRecipe":false,"commentCount":0},{"id":5561,"slug":"mieliekoekies","title":"Mieliekoekies","date":"2019-06-12T17:15:23","excerpt":"","categories":[33,6],"tags":[234,235],"featured":null,"hasRecipe":false,"commentCount":0},{"id":5564,"slug":"varkballetjies-met-doopsous","title":"Varkballetjies met Doopsous","date":"2019-06-12T17:15:08","excerpt":"","categories":[14],"tags":[238,237,236],"featured":null,"hasRecipe":false,"commentCount":0},{"id":5556,"slug":"sjokolade-fondant","title":"Sjokolade-fondant","date":"2019-06-05T17:15:27","excerpt":"","categories":[8],"tags":[233,232],"featured":null,"hasRecipe":false,"commentCount":0},{"id":5552,"slug":"boerington-met-sampioen-kruiesous","title":"Boerington met Sampioen-kruiesous","date":"2019-06-05T17:15:18","excerpt":"","categories":[11],"tags":[230,231,184],"featured":null,"hasRecipe":false,"commentCount":0},{"id":5524,"slug":"griekse-slaai","title":"Griekse Slaai","date":"2019-05-29T17:15:16","excerpt":"","categories":[33],"tags":[229,228,97],"featured":null,"hasRecipe":false,"commentCount":0},{"id":5521,"slug":"moussaka","title":"Moussaka","date":"2019-05-29T17:15:12","excerpt":"","categories":[5],"tags":[227,226,225],"featured":null,"hasRecipe":false,"commentCount":0},{"id":5515,"slug":"verdrinkte-koffieroomys","title":"Verdrinkte Koffieroomys","date":"2019-05-22T17:15:32","excerpt":"","categories":[8],"tags":[224,223,222,221],"featured":null,"hasRecipe":false,"commentCount":0},{"id":5511,"slug":"franse-uiesop","title":"Franse Uiesop","date":"2019-05-22T17:15:30","excerpt":"","categories":[6],"tags":[217,215,23,216],"featured":null,"hasRecipe":false,"commentCount":0},{"id":5505,"slug":"aspersie-eiers-en-mayonnaise","title":"Aspersie, Eiers en Mayonnaise","date":"2019-05-22T17:15:02","excerpt":"","categories":[16],"tags":[170,218,220,219],"featured":null,"hasRecipe":false,"commentCount":0},{"id":5501,"slug":"sponssouskluitjies","title":"Sponssouskluitjies","date":"2019-05-15T17:15:59","excerpt":"","categories":[8],"tags":[214,72,213,212],"featured":null,"hasRecipe":false,"commentCount":0},{"id":5498,"slug":"koeskoesslaai","title":"Koeskoesslaai","date":"2019-05-15T17:15:21","excerpt":"","categories":[33],"tags":[210,211,97],"featured":null,"hasRecipe":false,"commentCount":0},{"id":5495,"slug":"suurlemoenhoender","title":"Suurlemoenhoender","date":"2019-05-15T17:15:00","excerpt":"","categories":[7],"tags":[27,209],"featured":null,"hasRecipe":false,"commentCount":0},{"id":5350,"slug":"hot-cross-bun-broodpoeding","title":"Hot cross bun broodpoeding","date":"2019-03-25T15:18:41","excerpt":"","categories":[5,8],"tags":[],"featured":null,"hasRecipe":false,"commentCount":0},{"id":5345,"slug":"druiwekonfyt","title":"Druiwekonfyt","date":"2019-02-10T21:04:30","excerpt":"","categories":[33],"tags":[],"featured":null,"hasRecipe":false,"commentCount":16},{"id":5334,"slug":"bolognesesous","title":"Bolognesesous","date":"2019-01-24T17:25:46","excerpt":"","categories":[309],"tags":[],"featured":null,"hasRecipe":false,"commentCount":2},{"id":5340,"slug":"ons-cassata","title":"Ons Cassata","date":"2019-01-24T17:25:11","excerpt":"","categories":[8],"tags":[119],"featured":null,"hasRecipe":false,"commentCount":0},{"id":5330,"slug":"maklik-met-marinda-johann-engelbrecht","title":"Maklik Met Marinda – Johann Engelbrecht","date":"2019-01-22T13:17:57","excerpt":"","categories":[36],"tags":[118,55],"featured":null,"hasRecipe":false,"commentCount":6},{"id":5324,"slug":"suurlemoen-posset","title":"Suurlemoen Posset","date":"2019-01-20T21:09:25","excerpt":"","categories":[8],"tags":[117,24],"featured":null,"hasRecipe":false,"commentCount":0},{"id":5317,"slug":"oreotruffels","title":"Oreotruffels","date":"2019-01-17T17:25:50","excerpt":"","categories":[8],"tags":[115,116,114],"featured":null,"hasRecipe":false,"commentCount":0},{"id":5314,"slug":"geroosterde-blomkool-en-tamatieslaai","title":"Geroosterde Blomkool- en Tamatieslaai","date":"2019-01-17T17:25:27","excerpt":"","categories":[12],"tags":[113,97,92],"featured":null,"hasRecipe":false,"commentCount":0},{"id":5309,"slug":"romerige-bloukaashoender","title":"Romerige Bloukaashoender","date":"2019-01-17T17:25:07","excerpt":"","categories":[7],"tags":[112,27,111],"featured":null,"hasRecipe":false,"commentCount":0},{"id":5305,"slug":"maklik-met-marinda-nicole-holm","title":"Maklik Met Marinda – Nicole Holm","date":"2019-01-11T12:42:45","excerpt":"","categories":[36],"tags":[55,111],"featured":null,"hasRecipe":false,"commentCount":0},{"id":5299,"slug":"rooiwynsous","title":"Rooiwynsous","date":"2019-01-10T17:25:56","excerpt":"","categories":[33],"tags":[105,106,72],"featured":null,"hasRecipe":false,"commentCount":0},{"id":5294,"slug":"steakpastei","title":"Steakpastei","date":"2019-01-10T17:25:20","excerpt":"","categories":[11],"tags":[102,104,101,100],"featured":null,"hasRecipe":false,"commentCount":0},{"id":5302,"slug":"slaptjips","title":"Slaptjips","date":"2019-01-10T17:25:01","excerpt":"","categories":[33],"tags":[108,110,109,107],"featured":null,"hasRecipe":false,"commentCount":0},{"id":5289,"slug":"maklik-met-marinda-wicus-van-der-merwe","title":"Maklik Met Marinda – Wicus van der Merwe","date":"2018-12-20T17:23:23","excerpt":"","categories":[36],"tags":[55,103],"featured":null,"hasRecipe":false,"commentCount":0},{"id":5277,"slug":"tamatie-bloukaastert","title":"Tamatie-Bloukaastert","date":"2018-12-13T17:25:24","excerpt":"","categories":[33,5],"tags":[93,95,92,94],"featured":null,"hasRecipe":false,"commentCount":0},{"id":5284,"slug":"ultimate-slaaisous","title":"Ultimate Slaaisous","date":"2018-12-13T17:25:07","excerpt":"","categories":[33,12],"tags":[98,99],"featured":null,"hasRecipe":false,"commentCount":5},{"id":5282,"slug":"broccolislaai","title":"Broccolislaai","date":"2018-12-13T17:25:05","excerpt":"","categories":[33,12],"tags":[96,97],"featured":null,"hasRecipe":false,"commentCount":2},{"id":5273,"slug":"maklik-met-marinda-esther-von-waltsleben","title":"Maklik Met Marinda – Esther von Waltsleben","date":"2018-12-13T11:35:57","excerpt":"","categories":[36],"tags":[91,55],"featured":null,"hasRecipe":false,"commentCount":0},{"id":5269,"slug":"soetsuur-lewer","title":"Soetsuur Lewer","date":"2018-12-06T17:25:32","excerpt":"","categories":[11],"tags":[87,88],"featured":null,"hasRecipe":false,"commentCount":6},{"id":5261,"slug":"murgbene-kappertjiesalsa","title":"Murgbene en Kappertjiesalsa","date":"2018-12-06T17:25:18","excerpt":"","categories":[33],"tags":[85,84,86],"featured":null,"hasRecipe":false,"commentCount":2},{"id":5271,"slug":"niertjiesmoor","title":"Niertjiesmoor","date":"2018-12-06T17:25:05","excerpt":"","categories":[11],"tags":[90,89],"featured":null,"hasRecipe":false,"commentCount":0},{"id":5257,"slug":"maklik-met-marinda-herman-binge","title":"Maklik Met Marinda – Herman Binge","date":"2018-12-06T16:38:57","excerpt":"","categories":[36],"tags":[83,55],"featured":null,"hasRecipe":false,"commentCount":1},{"id":5244,"slug":"boeta-se-skaapboud","title":"Boeta se Skaapboud","date":"2018-11-29T17:25:25","excerpt":"","categories":[11],"tags":[79,78],"featured":null,"hasRecipe":false,"commentCount":0},{"id":5236,"slug":"marinda-se-varklies","title":"Marinda se Varklies","date":"2018-11-29T17:25:06","excerpt":"","categories":[308,14],"tags":[55,77,76],"featured":null,"hasRecipe":false,"commentCount":2},{"id":5247,"slug":"anna-se-beeslende","title":"Anna se Beeslende","date":"2018-11-29T17:25:06","excerpt":"","categories":[11],"tags":[80,81,55],"featured":null,"hasRecipe":false,"commentCount":4},{"id":5252,"slug":"maklik-met-marinda-michele-steyn","title":"Maklik Met Marinda – Michele Steyn","date":"2018-11-29T15:57:23","excerpt":"","categories":[36],"tags":[55,82],"featured":null,"hasRecipe":false,"commentCount":0},{"id":5232,"slug":"appelkooskonfyt","title":"Appelkooskonfyt","date":"2018-11-29T15:22:33","excerpt":"","categories":[33],"tags":[75],"featured":null,"hasRecipe":false,"commentCount":0},{"id":5219,"slug":"parmesaan-visfilette","title":"Parmesaan-visfilette","date":"2018-11-22T17:25:38","excerpt":"","categories":[30],"tags":[68,70,69],"featured":null,"hasRecipe":false,"commentCount":2},{"id":5227,"slug":"suurlemoenrisotto","title":"Suurlemoenrisotto","date":"2018-11-22T17:25:20","excerpt":"","categories":[33],"tags":[73,24,74],"featured":null,"hasRecipe":false,"commentCount":0},{"id":5225,"slug":"witbottersous","title":"Witbottersous","date":"2018-11-22T17:25:15","excerpt":"","categories":[33],"tags":[72,71],"featured":null,"hasRecipe":false,"commentCount":0},{"id":5214,"slug":"maklik-met-marinda-haidee-muller","title":"Maklik Met Marinda – Haidee Muller","date":"2018-11-22T10:35:57","excerpt":"","categories":[36],"tags":[68,55],"featured":null,"hasRecipe":false,"commentCount":0},{"id":5211,"slug":"vinnige-ciabatta","title":"Vinnige Ciabatta","date":"2018-11-15T17:59:58","excerpt":"","categories":[33],"tags":[56,67,63,55],"featured":null,"hasRecipe":false,"commentCount":0},{"id":5199,"slug":"rissiesous","title":"Rissiesous","date":"2018-11-15T17:29:54","excerpt":"","categories":[33],"tags":[63,55,64],"featured":null,"hasRecipe":false,"commentCount":4},{"id":5209,"slug":"rissiehoenderlewers","title":"Rissiehoenderlewers","date":"2018-11-15T17:29:27","excerpt":"","categories":[7],"tags":[66,63,55,65],"featured":null,"hasRecipe":false,"commentCount":2},{"id":5195,"slug":"maklik-met-marinda-kevin-leo","title":"Maklik Met Marinda – Kevin Leo","date":"2018-11-09T11:20:00","excerpt":"","categories":[36],"tags":[63,55],"featured":null,"hasRecipe":false,"commentCount":0},{"id":5180,"slug":"ansjoviskaasbrood","title":"Ansjoviskaasbrood","date":"2018-11-08T17:20:57","excerpt":"","categories":[33],"tags":[59,58],"featured":null,"hasRecipe":false,"commentCount":0},{"id":5189,"slug":"kaasstrooitjies","title":"Kaasstrooitjies","date":"2018-11-08T17:20:48","excerpt":"","categories":[33],"tags":[60,58],"featured":null,"hasRecipe":false,"commentCount":4},{"id":5191,"slug":"rokerige-tamatiesop","title":"Rokerige Tamatiesop","date":"2018-11-08T17:20:12","excerpt":"","categories":[33,16],"tags":[62,61,23],"featured":null,"hasRecipe":false,"commentCount":0},{"id":5176,"slug":"maklik-met-marinda-mariana-du-preez","title":"Maklik Met Marinda – Mariana Du Preez","date":"2018-11-08T15:33:00","excerpt":"","categories":[36],"tags":[58],"featured":null,"hasRecipe":false,"commentCount":0},{"id":5170,"slug":"maklike-brood","title":"Brood met steengemaalde meel","date":"2018-11-05T14:32:18","excerpt":"","categories":[314,5],"tags":[56,57],"featured":null,"hasRecipe":false,"commentCount":0},{"id":5156,"slug":"murgpampoentjietert","title":"Murgpampoentjietert","date":"2018-11-01T17:30:50","excerpt":"","categories":[33],"tags":[51,53],"featured":null,"hasRecipe":false,"commentCount":0},{"id":5160,"slug":"sagopoeding","title":"Sagopoeding","date":"2018-11-01T17:30:22","excerpt":"","categories":[5,8],"tags":[51,54],"featured":null,"hasRecipe":false,"commentCount":8},{"id":5145,"slug":"hoenderlensiesop","title":"Hoenderlensiesop","date":"2018-11-01T17:30:01","excerpt":"","categories":[7,16],"tags":[27,52,51],"featured":null,"hasRecipe":false,"commentCount":0},{"id":5162,"slug":"maklik-met-marinda-marlene-le-roux","title":"Maklik Met Marinda – Marlene le Roux","date":"2018-11-01T17:26:45","excerpt":"","categories":[36],"tags":[55,51],"featured":null,"hasRecipe":false,"commentCount":0},{"id":5138,"slug":"krummelappeltert","title":"Krummelappeltert","date":"2018-10-25T17:30:38","excerpt":"","categories":[5],"tags":[50,49,48,43],"featured":null,"hasRecipe":false,"commentCount":4},{"id":5134,"slug":"konsertinapatats","title":"Konsertinapatats","date":"2018-10-25T17:30:32","excerpt":"","categories":[33],"tags":[47,43],"featured":null,"hasRecipe":false,"commentCount":0},{"id":5130,"slug":"zakkie-se-smoorsnoek","title":"Zakkie se Smoorsnoek","date":"2018-10-25T17:30:12","excerpt":"","categories":[30],"tags":[46,43],"featured":null,"hasRecipe":false,"commentCount":0},{"id":5126,"slug":"maklik-met-marinda-zakkie-bester","title":"Maklik Met Marinda – Zakkie Bester","date":"2018-10-22T15:41:41","excerpt":"","categories":[36],"tags":[45,44,43],"featured":null,"hasRecipe":false,"commentCount":0},{"id":5109,"slug":"geroosterde-groente","title":"Geroosterde Groente","date":"2018-10-18T17:30:30","excerpt":"","categories":[33,6],"tags":[35],"featured":null,"hasRecipe":false,"commentCount":2},{"id":5102,"slug":"beesstert","title":"Beesstert","date":"2018-10-18T17:30:05","excerpt":"","categories":[11],"tags":[32],"featured":null,"hasRecipe":false,"commentCount":2},{"id":5106,"slug":"polentavingers","title":"Polentavingers","date":"2018-10-18T17:30:02","excerpt":"","categories":[33],"tags":[34],"featured":null,"hasRecipe":false,"commentCount":0},{"id":5120,"slug":"maklik-met-marinda-margit-meyer-rodenbeck","title":"Maklik Met Marinda – Margit Meyer-Rödenbeck","date":"2018-10-18T11:45:09","excerpt":"","categories":[36],"tags":[32,35,40,42,41],"featured":null,"hasRecipe":false,"commentCount":0},{"id":5115,"slug":"maklik-met-marinda-louise-engelbrecht","title":"Maklik Met Marinda – Louise Engelbrecht","date":"2018-10-18T11:38:12","excerpt":"","categories":[36],"tags":[37,39,38],"featured":null,"hasRecipe":false,"commentCount":0},{"id":5084,"slug":"romerige-mossels","title":"Romerige Mossels","date":"2018-10-11T16:20:19","excerpt":"","categories":[30],"tags":[31,28],"featured":null,"hasRecipe":false,"commentCount":5},{"id":5080,"slug":"broccolihoender","title":"Broccolihoender","date":"2018-10-11T16:15:32","excerpt":"","categories":[7],"tags":[29,27,28],"featured":null,"hasRecipe":true,"commentCount":4},{"id":5075,"slug":"macaroni-kaas","title":"Macaroni en Kaas","date":"2018-10-11T16:08:02","excerpt":"","categories":[322],"tags":[],"featured":null,"hasRecipe":true,"commentCount":10},{"id":5492,"slug":"oosterse-hoenderrepies","title":"Oosterse Hoenderrepies","date":"2018-07-05T16:01:14","excerpt":"","categories":[7],"tags":[208,207],"featured":null,"hasRecipe":false,"commentCount":0},{"id":5489,"slug":"groen-hoenderkerrie","title":"Groen Hoenderkerrie","date":"2018-07-05T15:56:16","excerpt":"","categories":[7],"tags":[205,206],"featured":null,"hasRecipe":false,"commentCount":0},{"id":5486,"slug":"groenkerriepasta","title":"Groenkerriepasta","date":"2018-07-05T15:21:08","excerpt":"","categories":[33],"tags":[203,202,204],"featured":null,"hasRecipe":false,"commentCount":0},{"id":5481,"slug":"peerstrudeltjies","title":"Peerstrudeltjies","date":"2018-06-28T15:16:04","excerpt":"","categories":[8],"tags":[201],"featured":null,"hasRecipe":false,"commentCount":0},{"id":5478,"slug":"kaas-en-uiebroodjie","title":"Kaas- en Uiebroodjie","date":"2018-06-28T15:11:36","excerpt":"","categories":[33,5],"tags":[200],"featured":null,"hasRecipe":false,"commentCount":0},{"id":5474,"slug":"veelsydige-slap-degie","title":"Veelsydige Slap Degie","date":"2018-06-28T15:04:49","excerpt":"","categories":[5],"tags":[199,198],"featured":null,"hasRecipe":false,"commentCount":0},{"id":5471,"slug":"hoenderworsie-suurlemoenpasta","title":"Hoenderworsie & Suurlemoenpasta","date":"2018-06-21T14:59:02","excerpt":"","categories":[7],"tags":[196,195,197],"featured":null,"hasRecipe":false,"commentCount":0},{"id":5468,"slug":"kerriefrikkadelle","title":"Kerriefrikkadelle","date":"2018-06-21T14:53:20","excerpt":"","categories":[308],"tags":[194,131,193],"featured":null,"hasRecipe":false,"commentCount":0},{"id":5465,"slug":"varkworsies-met-bbq-uie","title":"Varkworsies met BBQ-uie","date":"2018-06-21T14:46:40","excerpt":"","categories":[14],"tags":[192,191,190],"featured":null,"hasRecipe":false,"commentCount":0},{"id":5462,"slug":"creme-brulee","title":"Crème Brûlée","date":"2018-06-14T14:39:34","excerpt":"","categories":[5,8],"tags":[189],"featured":null,"hasRecipe":false,"commentCount":0},{"id":5459,"slug":"ma-se-visvorm","title":"Ma se Visvorm","date":"2018-06-14T14:35:37","excerpt":"","categories":[33],"tags":[186,188,187],"featured":null,"hasRecipe":false,"commentCount":0},{"id":5456,"slug":"romerige-sampioensous","title":"Romerige Sampioensous","date":"2018-06-14T14:34:31","excerpt":"","categories":[33],"tags":[185,183,184],"featured":null,"hasRecipe":false,"commentCount":0},{"id":5453,"slug":"ma-se-hoenderpastei","title":"Ma se Hoenderpastei","date":"2018-06-07T14:23:13","excerpt":"","categories":[7],"tags":[182,181],"featured":null,"hasRecipe":false,"commentCount":0},{"id":5450,"slug":"gebakte-pampoenskywe","title":"Gebakte Pampoenskywe","date":"2018-06-07T14:18:23","excerpt":"","categories":[33,6],"tags":[178,180,179],"featured":null,"hasRecipe":false,"commentCount":0},{"id":5447,"slug":"gebakte-aartappels","title":"Gebakte Aartappels","date":"2018-06-07T13:57:54","excerpt":"","categories":[33,6],"tags":[177,176],"featured":null,"hasRecipe":false,"commentCount":0},{"id":5444,"slug":"vis-in-bierbeslag","title":"Vis in Bierbeslag","date":"2018-05-31T13:49:24","excerpt":"","categories":[30],"tags":[175,171,174],"featured":null,"hasRecipe":false,"commentCount":0},{"id":5440,"slug":"maklike-viskoekies","title":"Maklike Viskoekies","date":"2018-05-31T13:43:04","excerpt":"","categories":[30],"tags":[172,173],"featured":null,"hasRecipe":false,"commentCount":0},{"id":5437,"slug":"gebakte-aspersievis","title":"Gebakte Aspersievis","date":"2018-05-31T13:24:16","excerpt":"","categories":[30],"tags":[170,169,168,171],"featured":null,"hasRecipe":false,"commentCount":0},{"id":5434,"slug":"steri-stumpie-stolpoeding","title":"Steri Stumpie Stolpoeding","date":"2018-05-24T13:18:25","excerpt":"","categories":[8],"tags":[167,165,164,166],"featured":null,"hasRecipe":false,"commentCount":0},{"id":5431,"slug":"klapper-panna-cotta","title":"Klapper Panna Cotta","date":"2018-05-24T13:14:05","excerpt":"","categories":[8],"tags":[],"featured":null,"hasRecipe":false,"commentCount":0},{"id":5428,"slug":"kaaskoekrolletjies","title":"Kaaskoekrolletjies","date":"2018-05-24T13:03:29","excerpt":"","categories":[5,8],"tags":[163,162],"featured":null,"hasRecipe":false,"commentCount":0},{"id":5425,"slug":"foccacia-in-drie-dele","title":"Foccacia in Drie Dele","date":"2018-05-17T12:57:48","excerpt":"","categories":[33,6],"tags":[161],"featured":null,"hasRecipe":false,"commentCount":0},{"id":5422,"slug":"calzone-met-salsa","title":"Calzone met Salsa","date":"2018-05-17T12:50:21","excerpt":"","categories":[6,7],"tags":[160,159,86],"featured":null,"hasRecipe":false,"commentCount":0},{"id":5419,"slug":"bokkenfolle","title":"Bokkenfolle","date":"2018-05-17T12:45:39","excerpt":"","categories":[5],"tags":[158],"featured":null,"hasRecipe":false,"commentCount":0},{"id":5416,"slug":"seekos-sop","title":"Seekos-sop","date":"2018-05-10T12:17:10","excerpt":"","categories":[30],"tags":[157,156,23],"featured":null,"hasRecipe":false,"commentCount":0},{"id":5413,"slug":"gerookte-makrielpatee","title":"Gerookte Makrielpatee","date":"2018-05-10T12:12:57","excerpt":"","categories":[33,30,16],"tags":[153,154,155],"featured":null,"hasRecipe":false,"commentCount":0},{"id":5410,"slug":"vis-en-patatpastei","title":"Vis- en Patatpastei","date":"2018-05-10T12:03:44","excerpt":"","categories":[30],"tags":[102,152,150,151],"featured":null,"hasRecipe":false,"commentCount":0},{"id":5406,"slug":"babbelas-bunny-chow-bobotie","title":"Babbelas Bunny Chow-bobotie","date":"2018-05-03T15:38:25","excerpt":"","categories":[308],"tags":[149,147,143,148],"featured":null,"hasRecipe":false,"commentCount":0},{"id":5403,"slug":"oorskietlamsbobotie","title":"Oorskietlamsbobotie","date":"2018-05-03T15:28:53","excerpt":"","categories":[308,270],"tags":[120,146,145,144],"featured":null,"hasRecipe":false,"commentCount":0},{"id":5399,"slug":"vark-en-appel-bobotie","title":"Vark-en-Appel Bobotie","date":"2018-05-03T12:06:18","excerpt":"","categories":[14],"tags":[143,77,142],"featured":null,"hasRecipe":false,"commentCount":0},{"id":5396,"slug":"boksie-creme-caramel","title":"Boksie Crème Caramel","date":"2018-04-26T15:33:38","excerpt":"","categories":[8],"tags":[140,141],"featured":null,"hasRecipe":false,"commentCount":0},{"id":5393,"slug":"fattoush","title":"Fattoush","date":"2018-04-26T15:23:24","excerpt":"","categories":[12],"tags":[138,139],"featured":null,"hasRecipe":false,"commentCount":0},{"id":5388,"slug":"spinasie-okkasiekoek","title":"Spinasie-okkasiekoek","date":"2018-04-26T15:22:51","excerpt":"","categories":[6],"tags":[137,136,135],"featured":null,"hasRecipe":false,"commentCount":0},{"id":5385,"slug":"botterskorsiegebak","title":"Botterskorsiegebak","date":"2018-04-19T16:47:35","excerpt":"","categories":[5],"tags":[133,132,134],"featured":null,"hasRecipe":false,"commentCount":0},{"id":5382,"slug":"kerrie-afval","title":"Kerrie Afval","date":"2018-04-19T16:41:02","excerpt":"","categories":[308],"tags":[129,131,130],"featured":null,"hasRecipe":false,"commentCount":0},{"id":5379,"slug":"nie-jou-ma-se-bone","title":"Nie jou Ma se Bone","date":"2018-04-19T16:32:15","excerpt":"","categories":[6],"tags":[127,128,126],"featured":null,"hasRecipe":false,"commentCount":0},{"id":5375,"slug":"lam-koftas","title":"Lam Koftas","date":"2018-04-12T16:23:46","excerpt":"","categories":[11],"tags":[125,120,124],"featured":null,"hasRecipe":false,"commentCount":0},{"id":5372,"slug":"rokerige-lams-oondpot","title":"Rokerige Lams-oondpot","date":"2018-04-12T16:15:45","excerpt":"","categories":[11],"tags":[120,122,123],"featured":null,"hasRecipe":false,"commentCount":0},{"id":5361,"slug":"lam-in-n-sak","title":"Lam in ’n Sak","date":"2018-04-12T15:47:36","excerpt":"","categories":[11],"tags":[120],"featured":null,"hasRecipe":false,"commentCount":0},{"id":2314,"slug":"soetmostert-3-bestandele-jy-gaan-nooit-weer-terugkyk-nie","title":"Soetmostert – 3 bestandele – jy gaan nooit weer terugkyk nie.","date":"2016-01-10T16:25:24","excerpt":"","categories":[33],"tags":[],"featured":null,"hasRecipe":false,"commentCount":0},{"id":2305,"slug":"pizza-oor-die-kole-geen-resep-maklik","title":"Pizza oor die kole – geen resep maklik","date":"2015-11-01T07:11:52","excerpt":"","categories":[5,315],"tags":[],"featured":null,"hasRecipe":false,"commentCount":0},{"id":2286,"slug":"appeltertjies","title":"Appeltertjies","date":"2015-10-12T19:28:18","excerpt":"","categories":[5,317,8],"tags":[],"featured":null,"hasRecipe":false,"commentCount":0},{"id":2275,"slug":"kerrie-noodle-slaai-hou-vir-lank-in-die-yskas","title":"Kerrie noodleslaai  – hou vir lank in die yskas","date":"2015-06-28T08:38:20","excerpt":"","categories":[33,12],"tags":[131,365],"featured":null,"hasRecipe":true,"commentCount":49},{"id":2273,"slug":"tamatiesop-smaak-soos-woolies-sin","title":"Tamatiesop -smaak soos Woolies sin","date":"2015-06-15T07:38:43","excerpt":"","categories":[310,16],"tags":[],"featured":null,"hasRecipe":false,"commentCount":0},{"id":2272,"slug":"banting-chocolate-brownies-dit-voel-nie-soos-verneuk-nie","title":"Banting chocolate brownies – dit voel nie soos verneuk nie.","date":"2015-06-07T08:45:17","excerpt":"","categories":[5,8],"tags":[],"featured":null,"hasRecipe":false,"commentCount":0},{"id":2271,"slug":"banting-sjokolade-mousse-gemaak-met-avo","title":"Banting sjokolademousse – Gemaak met avo!!!!!!!!","date":"2015-05-29T19:05:42","excerpt":"","categories":[8],"tags":[361,362,363],"featured":null,"hasRecipe":false,"commentCount":0},{"id":2270,"slug":"steri-stumpie-poeding-van-mari-louis-guy","title":"Steri Stumpie-poeding  – van Mari- Louis Guy","date":"2015-05-18T12:59:05","excerpt":"","categories":[8],"tags":[],"featured":null,"hasRecipe":false,"commentCount":0},{"id":2269,"slug":"butterscotch-sous-vir-roomys-3-bestandele","title":"Butterscotch-sous vir roomys – 3 bestanddele","date":"2015-05-10T15:53:24","excerpt":"","categories":[8],"tags":[72],"featured":null,"hasRecipe":false,"commentCount":0},{"id":2268,"slug":"donderdag-se-lip-aflek-vinnige-hoender","title":"Donderdag se lip-aflek vinnige hoender","date":"2015-04-16T13:28:29","excerpt":"","categories":[7,308],"tags":[27],"featured":null,"hasRecipe":false,"commentCount":18},{"id":2267,"slug":"skaapstertjies-blinkbruin","title":"Skaapstertjies – blinkbruin","date":"2015-04-01T12:10:59","excerpt":"","categories":[308,11,270],"tags":[271],"featured":null,"hasRecipe":false,"commentCount":0},{"id":2266,"slug":"guinness-wortelbredie-nou-wat-kan-lekkerder","title":"Guinness wortelbredie  – nou wat kan lekkerder?","date":"2015-03-30T09:10:55","excerpt":"","categories":[308,11],"tags":[364],"featured":null,"hasRecipe":false,"commentCount":2},{"id":2265,"slug":"panna-cotta-vir-banters-en-ander","title":"Panna Cotta vir banters – en ander","date":"2015-03-29T08:46:59","excerpt":"","categories":[8],"tags":[342],"featured":null,"hasRecipe":false,"commentCount":0},{"id":2151,"slug":"vinnige-maandag-hoender-bruin-en-lekker","title":"Vinnige Maandaghoender – bruin en lekker","date":"2015-03-23T14:58:13","excerpt":"","categories":[7,308],"tags":[27],"featured":null,"hasRecipe":false,"commentCount":0},{"id":2119,"slug":"brood-en-botterpoeding-vra-vir-nog","title":"Brood-en-botterpoeding – vra vir nog","date":"2015-03-16T08:20:49","excerpt":"","categories":[5,8],"tags":[],"featured":null,"hasRecipe":false,"commentCount":0},{"id":2098,"slug":"aartappelslaai-o-aartappelslaai","title":"Aartappelslaai – o, aartappelslaai","date":"2015-02-24T20:24:30","excerpt":"","categories":[12],"tags":[],"featured":null,"hasRecipe":true,"commentCount":0},{"id":2082,"slug":"rocky-road-my-soettand-kry-die-oorhand","title":"Rocky road – my soettand kry die oorhand","date":"2015-02-16T15:35:25","excerpt":"","categories":[5,8],"tags":[],"featured":null,"hasRecipe":false,"commentCount":0},{"id":2062,"slug":"ongebakte-kaaskoek-mooi-en-lekker-en-vinnig","title":"Ongebakte kaaskoek –  mooi en lekker en vinnig","date":"2015-02-16T07:03:05","excerpt":"","categories":[5,316,8],"tags":[163],"featured":null,"hasRecipe":false,"commentCount":9},{"id":2049,"slug":"bak-n-kaas-knoffel-en-eet","title":"Bak ‘n kaas  – knoffel en eet","date":"2015-02-08T08:39:44","excerpt":"","categories":[33,16],"tags":[355],"featured":null,"hasRecipe":false,"commentCount":2},{"id":2029,"slug":"wit-sjokolade-dekadensie-glo-my-dis-lekkerder-as-lekker","title":"Wit sjokelade dekadensie – glo my dis lekkerder as lekker","date":"2015-02-04T20:04:02","excerpt":"","categories":[8],"tags":[233],"featured":null,"hasRecipe":false,"commentCount":0},{"id":2024,"slug":"sticky-varkstrippies-braai-dit-vandag","title":"Sticky varkrepies – braai dit vandag","date":"2015-01-11T05:51:57","excerpt":"","categories":[308,14],"tags":[77],"featured":null,"hasRecipe":false,"commentCount":5},{"id":2006,"slug":"kondensmelk-melktert-geen-bak-nodig","title":"Kondensmelk melktert – geen bak nodig","date":"2015-01-10T11:01:47","excerpt":"","categories":[8,319],"tags":[],"featured":null,"hasRecipe":false,"commentCount":8},{"id":1971,"slug":"cajun-hoender-vinnig-vir-n-maandagaand","title":"Cajun-hoender – vinnig vir n Maandagaand","date":"2015-01-05T19:52:02","excerpt":"","categories":[7,308],"tags":[356,27],"featured":null,"hasRecipe":false,"commentCount":0},{"id":1969,"slug":"braaibroodjies-tradisioneel-en-n-wenner","title":"Braaibroodjies – tradisioneel en n wenner","date":"2015-01-04T19:26:30","excerpt":"","categories":[33],"tags":[],"featured":null,"hasRecipe":false,"commentCount":0},{"id":1944,"slug":"sosaties-maak-dit-voor-die-vakansie-verby-is","title":"Sosaties – maak dit voor die vakansie verby is.","date":"2014-12-30T07:28:15","excerpt":"","categories":[11],"tags":[],"featured":null,"hasRecipe":false,"commentCount":2},{"id":1930,"slug":"gevulde-pepers-lekker-saam-met-n-slaai","title":"Gevulde pepers – lekker saam met n slaai","date":"2014-12-28T09:19:51","excerpt":"","categories":[33,6,11],"tags":[357],"featured":null,"hasRecipe":false,"commentCount":2},{"id":1920,"slug":"roosmaryn-tamatie-en-feta-gebak-iets-anders","title":"Roosmaryn, tamatie en feta-gebak – iets anders","date":"2014-12-07T19:04:36","excerpt":"","categories":[33,6,12,16],"tags":[],"featured":null,"hasRecipe":false,"commentCount":4},{"id":1899,"slug":"gammon-vir-krismis-en-vir-die-res-van-die-jaar","title":"Gammon vir Krismis – en vir die res van die jaar","date":"2014-12-03T19:56:27","excerpt":"","categories":[308,14],"tags":[358,359],"featured":null,"hasRecipe":true,"commentCount":55},{"id":1885,"slug":"banting-murgpampoen-soet-en-lekker","title":"Banting murgpampoen – soet en lekker","date":"2014-11-25T09:26:58","excerpt":"","categories":[33,6],"tags":[350],"featured":null,"hasRecipe":false,"commentCount":6},{"id":1871,"slug":"peppermintcrisp-tert-soos-van-ouds","title":"Peppermint crisp-tert  – soos van ouds","date":"2014-11-24T19:06:47","excerpt":"","categories":[5,8,319],"tags":[360],"featured":null,"hasRecipe":false,"commentCount":14},{"id":1853,"slug":"koolbredie-o-koolbredie","title":"Koolbredie – o, koolbredie","date":"2014-11-18T08:21:17","excerpt":"","categories":[11],"tags":[],"featured":null,"hasRecipe":true,"commentCount":35},{"id":1844,"slug":"porkbelly-met-kruie-en-suurlemoen","title":"Porkbelly – met kruie en suurlemoen","date":"2014-11-13T14:53:18","excerpt":"","categories":[308,14],"tags":[],"featured":null,"hasRecipe":false,"commentCount":0},{"id":1826,"slug":"krismis-kerrievis","title":"Krismis Kerrievis","date":"2014-11-11T06:36:26","excerpt":"","categories":[30],"tags":[],"featured":null,"hasRecipe":false,"commentCount":26},{"id":1818,"slug":"banting-patats-soet-en-lekker","title":"Banting patats – soet en lekker","date":"2014-10-07T18:21:21","excerpt":"","categories":[33,6],"tags":[350,264],"featured":null,"hasRecipe":false,"commentCount":10},{"id":1801,"slug":"songedroogte-tamatie-en-fetabrood-met-winkeldeeg","title":"Songedroogte tamatie-en-fetabrood – met winkeldeeg","date":"2014-09-24T12:26:36","excerpt":"","categories":[314,5],"tags":[56],"featured":null,"hasRecipe":false,"commentCount":0},{"id":1781,"slug":"aspersievis-heerlik-in-n-japtrap","title":"Aspersievis","date":"2014-09-16T08:20:26","excerpt":"","categories":[30],"tags":[],"featured":null,"hasRecipe":false,"commentCount":9},{"id":1764,"slug":"roompoffertjies-jy-kan-dit-bak","title":"Roompoffertjies  – jy kan dit bak","date":"2014-09-09T17:04:39","excerpt":"","categories":[5,8],"tags":[351],"featured":null,"hasRecipe":false,"commentCount":22},{"id":1747,"slug":"portugese-hoender-lekker-sterk-en-gou-gou","title":"Portugese hoender – lekker sterk en gou-gou","date":"2014-08-31T14:38:05","excerpt":"","categories":[7,308],"tags":[27,352],"featured":null,"hasRecipe":false,"commentCount":10},{"id":1722,"slug":"yskas-kaaskoek-bantingstyle","title":"Yskas-kaaskoek -Banting-style","date":"2014-07-26T09:56:00","excerpt":"","categories":[316,8],"tags":[163],"featured":null,"hasRecipe":false,"commentCount":6},{"id":1702,"slug":"brokkoli-sop-die-koue-kort-iets-dekadents","title":"Brokkolisop – die koue kort iets dekadents","date":"2014-07-08T10:15:21","excerpt":"","categories":[6,310,16],"tags":[353],"featured":null,"hasRecipe":false,"commentCount":8},{"id":1684,"slug":"groenboonbredie-net-reg-vir-die-koue","title":"Groenboonbredie  –  net reg vir die koue","date":"2014-06-24T14:21:53","excerpt":"","categories":[6,11],"tags":[],"featured":null,"hasRecipe":false,"commentCount":8},{"id":1668,"slug":"tjops-innie-oond-net-so-lekker-soos-op-die-vuur","title":"Tjops in die oond – net so lekker soos op die vuur","date":"2014-06-11T11:06:00","excerpt":"","categories":[308,11],"tags":[354],"featured":null,"hasRecipe":true,"commentCount":17},{"id":1643,"slug":"pampoenskywe-n-groot-lekkerte","title":"Pampoenskywe – ‘n groot lekkerte","date":"2014-06-02T11:12:26","excerpt":"","categories":[33,6],"tags":[179],"featured":null,"hasRecipe":false,"commentCount":6},{"id":1631,"slug":"tamatiesop-net-reg-vir-nou","title":"Tamatiesop – net reg vir nou","date":"2014-06-01T16:29:27","excerpt":"","categories":[33,6,310,16],"tags":[92],"featured":null,"hasRecipe":false,"commentCount":2},{"id":1614,"slug":"suurlemoenpoeding-winterwarmte","title":"Suurlemoenpoeding – winterwarmte","date":"2014-05-31T12:48:31","excerpt":"","categories":[5,8],"tags":[],"featured":null,"hasRecipe":false,"commentCount":10},{"id":1600,"slug":"roomys-3-bestandele","title":"Roomys – 3  bestandele","date":"2014-05-27T09:12:47","excerpt":"","categories":[8],"tags":[345],"featured":null,"hasRecipe":false,"commentCount":26},{"id":1577,"slug":"uie-marmelade-lekker-saam-met-alles","title":"Uie-marmelade – lekker saam met alles","date":"2014-05-26T16:24:05","excerpt":"","categories":[33,6],"tags":[],"featured":null,"hasRecipe":false,"commentCount":23},{"id":1561,"slug":"mayonnaise-so-maklik-soos-eiersklits","title":"Mayonnaise – so maklik soos eiersklits","date":"2014-05-22T09:42:16","excerpt":"","categories":[33],"tags":[],"featured":null,"hasRecipe":false,"commentCount":10},{"id":1545,"slug":"pannekoek-onfeilbaar","title":"Pannekoek – onfeilbaar","date":"2014-05-16T14:39:30","excerpt":"","categories":[8],"tags":[333],"featured":null,"hasRecipe":false,"commentCount":6},{"id":1527,"slug":"sticky-chicken-moeilik-om-te-vertaal-klewerigetaai-hoender","title":"Sticky chicken – moeilik om te vertaal (klewerige/taai hoender)","date":"2014-05-15T16:30:22","excerpt":"","categories":[7,308],"tags":[27],"featured":null,"hasRecipe":false,"commentCount":15},{"id":1512,"slug":"choc-pot-in-2-minute-mikrogolf","title":"Choc pot in 2 minute – mikrogolf","date":"2014-04-25T10:27:06","excerpt":"","categories":[5,8],"tags":[233],"featured":null,"hasRecipe":false,"commentCount":4},{"id":1498,"slug":"vinnige-vrydag-vis-alles-in-een-bak","title":"Vinnige Vrydagvis","date":"2014-04-25T08:43:53","excerpt":"","categories":[30],"tags":[],"featured":null,"hasRecipe":false,"commentCount":18},{"id":1491,"slug":"aartappelwiggies-met-paprika","title":"Aartappelwiggies – met paprika","date":"2014-04-24T08:50:01","excerpt":"","categories":[33,6],"tags":[343],"featured":null,"hasRecipe":false,"commentCount":3},{"id":1470,"slug":"bobotie-met-amandels-alles-in-een-bak","title":"Bobotie met amandels – alles in een bak","date":"2014-04-22T18:04:00","excerpt":"","categories":[308,11],"tags":[143],"featured":null,"hasRecipe":false,"commentCount":4},{"id":1457,"slug":"kerrie-afval-lymerig-lekker","title":"Kerrie-afval – lymerig lekker","date":"2014-04-16T11:09:16","excerpt":"","categories":[308,11],"tags":[129],"featured":null,"hasRecipe":false,"commentCount":11},{"id":1423,"slug":"coq-au-vin-hoender-met-n-dopskop","title":"Coq au vin – hoender met n dopskop","date":"2014-04-15T13:05:03","excerpt":"","categories":[7,308],"tags":[27],"featured":null,"hasRecipe":false,"commentCount":6},{"id":1425,"slug":"hawermoutkoekies-bly-n-gunsteling","title":"Hawermoutkoekies – bly ‘n gunsteling","date":"2014-04-09T08:59:45","excerpt":"","categories":[5,317],"tags":[282],"featured":null,"hasRecipe":true,"commentCount":32},{"id":1400,"slug":"ciabatta-met-dik-botter","title":"Ciabatta – met dik botter","date":"2014-04-07T16:04:42","excerpt":"","categories":[314,5],"tags":[56,67],"featured":null,"hasRecipe":true,"commentCount":38},{"id":1387,"slug":"piekeluie-maak-jou-eie-uie","title":"Gepekelde uie  – maak jou eie uie","date":"2014-03-24T12:53:04","excerpt":"","categories":[33,6],"tags":[190],"featured":null,"hasRecipe":false,"commentCount":10},{"id":1376,"slug":"dekadente-gesondheidsstafie-4-bestandele-net-oor-dit-langnaweek-is","title":"Dekadente gesondheidsstafie (4 bestandele) – net oor dit langnaweek is","date":"2014-03-22T15:33:27","excerpt":"","categories":[5],"tags":[],"featured":null,"hasRecipe":false,"commentCount":3},{"id":1361,"slug":"3-bestandele-piesangbrood-tog-te-lekker","title":"3 bestanddele piesangbrood – tog te lekker","date":"2014-03-18T16:40:49","excerpt":"","categories":[314,5],"tags":[56,324,344],"featured":null,"hasRecipe":false,"commentCount":13},{"id":1347,"slug":"roomys-2-bestandele-geen-suiwel","title":"Roomys – 2 bestanddele en geen suiwel","date":"2014-03-10T17:05:24","excerpt":"","categories":[8],"tags":[345],"featured":null,"hasRecipe":false,"commentCount":13},{"id":1336,"slug":"hoendersop-vir-gou-eet","title":"Hoendersop – vir gou eet","date":"2014-03-10T11:21:43","excerpt":"","categories":[7,310,16],"tags":[27],"featured":null,"hasRecipe":false,"commentCount":9},{"id":1318,"slug":"kool-en-kaas-herderspastei","title":"Kool-en-kaas-herderspastei","date":"2014-02-24T11:13:47","excerpt":"","categories":[308,11],"tags":[346],"featured":null,"hasRecipe":false,"commentCount":7},{"id":1293,"slug":"benoffee-tert-die-geilte-van-alle-geiltes","title":"Banoffie tert – die geilte van alle geiltes","date":"2014-02-22T13:16:41","excerpt":"","categories":[8],"tags":[324],"featured":null,"hasRecipe":false,"commentCount":4},{"id":1278,"slug":"ryspoeding-sommer-net-vir-lekker","title":"Ryspoeding – sommer net vir lekker","date":"2014-02-16T10:40:26","excerpt":"","categories":[8,321],"tags":[347],"featured":null,"hasRecipe":false,"commentCount":2},{"id":1266,"slug":"piesang-plaatkoekies-2-bestandele","title":"Piesang-plaatkoekies  – 2 bestandele","date":"2014-02-09T17:13:41","excerpt":"","categories":[5,8,332],"tags":[324],"featured":null,"hasRecipe":false,"commentCount":12},{"id":1252,"slug":"sjokoladeblokkies-3-bestandele","title":"SJOKOLADEBLOKKIES – 3 bestandele","date":"2014-02-07T11:43:17","excerpt":"","categories":[5],"tags":[],"featured":null,"hasRecipe":false,"commentCount":4},{"id":1236,"slug":"lamsribbetjie-oor-die-kole","title":"Lamsribbetjie – oor die kole","date":"2014-01-25T20:07:50","excerpt":"","categories":[308,11,270],"tags":[120],"featured":null,"hasRecipe":false,"commentCount":0},{"id":1216,"slug":"brandewyntert-brandewyn-is-nie-net-vir-coke-bedoel-nie","title":"Brandewyntert – brandewyn is nie net vir Coke bedoel nie","date":"2014-01-25T10:42:48","excerpt":"","categories":[5,8,319],"tags":[348],"featured":null,"hasRecipe":false,"commentCount":10},{"id":1203,"slug":"hoender-oor-die-kole-3-bestandele","title":"Hoender oor die kole – 3 bestandele","date":"2014-01-12T09:45:50","excerpt":"","categories":[7,308],"tags":[349,27],"featured":null,"hasRecipe":false,"commentCount":6},{"id":1187,"slug":"pampoenpoffertjies-wat-die-sous-opsuig","title":"Pampoenpoffertjies – wat die sous opsuig","date":"2014-01-11T14:03:54","excerpt":"","categories":[33,6],"tags":[],"featured":null,"hasRecipe":true,"commentCount":68},{"id":1167,"slug":"retro-tunavorm-mousse-n-lewensredder","title":"Retro Tunavorm Mousse","date":"2014-01-02T06:48:37","excerpt":"","categories":[30],"tags":[],"featured":null,"hasRecipe":false,"commentCount":14},{"id":1148,"slug":"rooisous-vir-pasta","title":"Rooisous vir pasta","date":"2013-12-29T09:29:30","excerpt":"","categories":[33,322,309],"tags":[72],"featured":null,"hasRecipe":false,"commentCount":4},{"id":1133,"slug":"die-sous-der-souse-meer-as-net-n-slaaisous","title":"Die sous der souse -meer as net n slaaisous","date":"2013-12-20T19:18:09","excerpt":"","categories":[33,12],"tags":[72],"featured":null,"hasRecipe":false,"commentCount":29},{"id":1109,"slug":"hoenderpastei","title":"Honderpastei","date":"2013-12-19T11:45:57","excerpt":"","categories":[7,308],"tags":[27],"featured":null,"hasRecipe":false,"commentCount":12},{"id":1085,"slug":"lasagne-ou-staatmaker","title":"Lasagne – ou staatmaker","date":"2013-12-18T13:31:53","excerpt":"","categories":[308,11],"tags":[],"featured":null,"hasRecipe":true,"commentCount":36},{"id":1080,"slug":"perfekte-gekookte-eiers-ja-dis-moontlik","title":"Perfekte gekookte eiers – ja dis moontlik","date":"2013-12-18T07:43:18","excerpt":"","categories":[332],"tags":[],"featured":null,"hasRecipe":false,"commentCount":8},{"id":1051,"slug":"roosterkoek-braaivleis-lekkerte","title":"Roosterkoek – braaivleis-lekkerte","date":"2013-12-08T19:57:07","excerpt":"","categories":[33,5],"tags":[338],"featured":null,"hasRecipe":false,"commentCount":13},{"id":1030,"slug":"lemoen-eend-tog-so-fensie","title":"Lemoen-eend – tog so fênsie","date":"2013-12-08T06:41:18","excerpt":"","categories":[7,308],"tags":[],"featured":null,"hasRecipe":false,"commentCount":6},{"id":1004,"slug":"rosewyn-en-aarbei-jellies-mooi-en-vars","title":"Roséwyn-en-aarbei-jellies – mooi en vars","date":"2013-12-08T05:35:08","excerpt":"","categories":[8],"tags":[340,339],"featured":null,"hasRecipe":false,"commentCount":4},{"id":987,"slug":"sjokoladeblokkies-dit-behoort-verban-te-word","title":"Sjokeladeblokkies – dit behoort verban te word","date":"2013-11-29T11:32:19","excerpt":"","categories":[8],"tags":[233],"featured":null,"hasRecipe":false,"commentCount":10},{"id":966,"slug":"paptert-verby-lekker","title":"Paptert – verby lekker","date":"2013-11-28T12:03:23","excerpt":"","categories":[33,5,319],"tags":[],"featured":null,"hasRecipe":true,"commentCount":31},{"id":950,"slug":"waaier-aartappels-bykos-vir-braai","title":"Waaier-aartappels – bykos vir braai","date":"2013-11-25T09:30:10","excerpt":"","categories":[33,6],"tags":[177],"featured":null,"hasRecipe":false,"commentCount":4},{"id":928,"slug":"frikadelle-rooies","title":"Frikkadelle – rooies","date":"2013-11-22T08:25:57","excerpt":"","categories":[308,11],"tags":[194],"featured":null,"hasRecipe":false,"commentCount":15},{"id":917,"slug":"soutvleis-vir-krismis","title":"Soutvleis – vir krismis","date":"2013-11-21T14:47:38","excerpt":"","categories":[308,11],"tags":[341],"featured":null,"hasRecipe":false,"commentCount":12},{"id":889,"slug":"braai-paai-so-lekker-oor-die-kole","title":"Braai paai – so lekker oor die kole","date":"2013-11-18T19:38:29","excerpt":"","categories":[33,319,16],"tags":[],"featured":null,"hasRecipe":false,"commentCount":14},{"id":883,"slug":"gemmerbier-sommer-vir-die-somer","title":"Gemmerbier – sommer vir die somer","date":"2013-11-16T08:29:24","excerpt":"","categories":[33],"tags":[],"featured":null,"hasRecipe":false,"commentCount":9},{"id":855,"slug":"tamatie-en-uieslaai-eerlike-kos","title":"Tamatie-en-uieslaai – eerlike kos","date":"2013-11-12T19:12:49","excerpt":"","categories":[33,12],"tags":[],"featured":null,"hasRecipe":false,"commentCount":13},{"id":829,"slug":"laat-ons-drink-likeur-die-soete-verleiding","title":"Laat ons drink – likeur die soete verleiding","date":"2013-11-12T13:32:42","excerpt":"","categories":[33,8],"tags":[],"featured":null,"hasRecipe":false,"commentCount":4},{"id":810,"slug":"kerrie-vark-braaitjops-my-diepste-uur","title":"Kerrie varkbraaitjops – my diepste uur","date":"2013-11-05T20:06:44","excerpt":"","categories":[308,14],"tags":[],"featured":null,"hasRecipe":false,"commentCount":19},{"id":798,"slug":"panna-cotta-happie-vir-happie","title":"Panna cotta – happie vir happie","date":"2013-11-04T17:47:02","excerpt":"","categories":[8],"tags":[342],"featured":null,"hasRecipe":false,"commentCount":0},{"id":785,"slug":"snoek-gerook-na-7-minute-is-jy-reg-vir-eet","title":"Snoek Gerook","date":"2013-10-29T08:12:38","excerpt":"","categories":[30],"tags":[],"featured":null,"hasRecipe":false,"commentCount":1},{"id":775,"slug":"soet-hoenderkerrie-gewone-kerrie-huiskerrie","title":"Soet hoenderkerrie – gewone kerrie, huiskerrie","date":"2013-10-21T18:12:30","excerpt":"","categories":[7,308],"tags":[27,131],"featured":null,"hasRecipe":true,"commentCount":41},{"id":755,"slug":"herderspastei-in-sy-eenvoud-lekker-huiskos","title":"Herderspastei – In sy eenvoud lekker huiskos","date":"2013-10-17T10:50:46","excerpt":"","categories":[313,5,308,11],"tags":[],"featured":null,"hasRecipe":true,"commentCount":44},{"id":737,"slug":"ma-se-groenboonbredie-en-koring","title":"Ma se groenboonbredie en koring","date":"2013-10-14T07:40:52","excerpt":"","categories":[308,11],"tags":[128],"featured":null,"hasRecipe":false,"commentCount":6},{"id":726,"slug":"marmelade-en-kaneel-pampoen","title":"Marmelade-en-kaneel-pampoen","date":"2013-10-12T20:46:00","excerpt":"","categories":[33,6],"tags":[],"featured":null,"hasRecipe":false,"commentCount":5},{"id":715,"slug":"sondaghoender-met-vulsel-wat-is-n-sondag-sonder-hoender","title":"Sondaghoender met vulsel – wat is n Sondag sonder hoender","date":"2013-10-08T10:18:48","excerpt":"","categories":[7,308],"tags":[],"featured":null,"hasRecipe":false,"commentCount":0},{"id":699,"slug":"sjokeladepoeding","title":"Warm sjokoladepoeding – Van my dae op die plaas","date":"2013-10-05T20:40:45","excerpt":"","categories":[5,8],"tags":[],"featured":null,"hasRecipe":false,"commentCount":15},{"id":682,"slug":"pere-in-rooiwyn-laat-die-aand-se-probleme-verdwyn","title":"Pere in rooiwyn – laat die aand se probleme verdwyn","date":"2013-09-28T10:36:40","excerpt":"","categories":[8],"tags":[],"featured":null,"hasRecipe":false,"commentCount":4},{"id":674,"slug":"drieboneslaai-windmakerig","title":"Drieboneslaai – windmakerig","date":"2013-09-26T10:13:08","excerpt":"","categories":[33,12],"tags":[],"featured":null,"hasRecipe":false,"commentCount":4},{"id":661,"slug":"botter-die-groot-versoeking","title":"Botter – die groot versoeking","date":"2013-09-23T14:30:21","excerpt":"","categories":[33],"tags":[],"featured":null,"hasRecipe":false,"commentCount":18},{"id":645,"slug":"pampoentert-jy-kry-krulhare-en-rooi-wange","title":"Pampoentert – jy kry krulhare en rooi wange","date":"2013-09-18T08:10:45","excerpt":"","categories":[33,6],"tags":[],"featured":null,"hasRecipe":true,"commentCount":33},{"id":625,"slug":"broccolihoender-my-kinders-se-gunsteling","title":"Broccolihoender – my kinders se gunsteling","date":"2013-09-16T11:24:22","excerpt":"","categories":[7,308],"tags":[],"featured":null,"hasRecipe":true,"commentCount":28},{"id":608,"slug":"fudge-met-grondboontjiebotter-en-chillie-10-minute-in-mikrogolf","title":"Fudge met grondboontjiebotter en chillie – 10 minute in mikrogolf","date":"2013-09-11T09:30:03","excerpt":"","categories":[8],"tags":[],"featured":null,"hasRecipe":false,"commentCount":6},{"id":589,"slug":"frikkadelle-met-kool-sielskos","title":"Frikkadelle met kool – sielskos","date":"2013-09-10T12:08:16","excerpt":"","categories":[308,11],"tags":[],"featured":null,"hasRecipe":false,"commentCount":8},{"id":561,"slug":"sagopoeding-padda-ogies","title":"Sagopoeding – Padda-ogies","date":"2013-09-01T12:36:30","excerpt":"","categories":[8],"tags":[],"featured":null,"hasRecipe":false,"commentCount":5},{"id":549,"slug":"lemon-meringue-soet-en-lekker","title":"Lemon meringue – soet en lekker","date":"2013-08-25T13:30:09","excerpt":"","categories":[5,319],"tags":[24,94],"featured":null,"hasRecipe":false,"commentCount":18},{"id":540,"slug":"butternutsop","title":"Butternutsop – met skop","date":"2013-08-22T18:35:32","excerpt":"","categories":[6,310,16],"tags":[20,23],"featured":null,"hasRecipe":false,"commentCount":12},{"id":505,"slug":"groenbone-met-botter","title":"Groenbone – met botter","date":"2013-08-21T04:45:29","excerpt":"","categories":[33,6],"tags":[],"featured":null,"hasRecipe":false,"commentCount":6},{"id":491,"slug":"skons-net-3-bestandele","title":"Skons – net 3 bestandele","date":"2013-08-17T09:57:18","excerpt":"","categories":[5],"tags":[337],"featured":null,"hasRecipe":true,"commentCount":37},{"id":481,"slug":"bloukaas-hoender-oeg-so-lekker","title":"Bloukaashoender – oeg so lekker","date":"2013-08-15T17:40:11","excerpt":"","categories":[7,308],"tags":[],"featured":null,"hasRecipe":false,"commentCount":15},{"id":421,"slug":"groente","title":"Groente – gesondheid uit die grond uit.","date":"2013-08-08T09:27:49","excerpt":"","categories":[6],"tags":[],"featured":null,"hasRecipe":false,"commentCount":2},{"id":429,"slug":"ertjiesop","title":"Ertjiesop – heel jaar deur","date":"2013-08-06T11:04:26","excerpt":"","categories":[310,16],"tags":[],"featured":null,"hasRecipe":true,"commentCount":35},{"id":403,"slug":"smoorsnoek","title":"Smoorsnoek","date":"2013-08-03T09:33:57","excerpt":"","categories":[30],"tags":[],"featured":null,"hasRecipe":false,"commentCount":3},{"id":387,"slug":"tbeen","title":"T-been steak  – reg op sy tyd","date":"2013-07-30T09:24:37","excerpt":"","categories":[308,11],"tags":[],"featured":null,"hasRecipe":false,"commentCount":0},{"id":370,"slug":"nutellabroodpoeding","title":"Nutella broodpoeding – spaar jou uit","date":"2013-07-26T19:50:04","excerpt":"","categories":[5,8],"tags":[334],"featured":null,"hasRecipe":false,"commentCount":4},{"id":354,"slug":"tamatiekos","title":"Tamatiekos – so van my ma af","date":"2013-07-24T12:33:46","excerpt":"","categories":[308,11],"tags":[],"featured":null,"hasRecipe":true,"commentCount":25},{"id":341,"slug":"bobotie","title":"Bobotie vir ete","date":"2013-07-22T11:46:37","excerpt":"","categories":[308,11],"tags":[143],"featured":null,"hasRecipe":true,"commentCount":57},{"id":334,"slug":"geelperskes","title":"Geelperskes in die Boland","date":"2013-07-15T06:40:08","excerpt":"","categories":[8,12],"tags":[],"featured":null,"hasRecipe":false,"commentCount":8},{"id":319,"slug":"porkbelly","title":"Porkbelly – gritssssss crackling","date":"2013-07-14T17:29:04","excerpt":"","categories":[308,14],"tags":[],"featured":null,"hasRecipe":false,"commentCount":16},{"id":313,"slug":"murgbene","title":"Murgbene- ryke, ryke lekkerte","date":"2013-07-13T12:18:26","excerpt":"","categories":[33,16],"tags":[],"featured":null,"hasRecipe":false,"commentCount":6},{"id":297,"slug":"maklikebrood","title":"Maklike brood – net 3 bestandele","date":"2013-07-12T08:08:06","excerpt":"","categories":[314,5],"tags":[56],"featured":null,"hasRecipe":true,"commentCount":42},{"id":279,"slug":"sjokoladedekadensie","title":"Sjokolade dekadensie – hy val waar hy wil","date":"2013-07-10T07:30:08","excerpt":"","categories":[8],"tags":[],"featured":null,"hasRecipe":false,"commentCount":12},{"id":267,"slug":"waterblommetjies","title":"Waterblommetjies in die Boland","date":"2013-07-08T12:13:37","excerpt":"","categories":[7,308],"tags":[],"featured":null,"hasRecipe":false,"commentCount":12},{"id":259,"slug":"appelpoeding","title":"Appelpoeding of namiddag tert","date":"2013-07-07T15:54:30","excerpt":"","categories":[5,8,319],"tags":[],"featured":null,"hasRecipe":false,"commentCount":7},{"id":257,"slug":"lamsblad","title":"Lamsblad – Elana Vermaak hier kom hy","date":"2013-07-06T06:36:17","excerpt":"","categories":[308,11,270],"tags":[120],"featured":null,"hasRecipe":false,"commentCount":13},{"id":244,"slug":"beet","title":"Wat het jy beet! – anderste lekker beet","date":"2013-07-04T12:33:33","excerpt":"","categories":[33,6],"tags":[335],"featured":null,"hasRecipe":false,"commentCount":3},{"id":234,"slug":"braaiaartappels","title":"Bruin braaiaartappels – njam,njam, njmmmmmmmm","date":"2013-07-03T11:19:27","excerpt":"","categories":[33,6],"tags":[177],"featured":null,"hasRecipe":false,"commentCount":2},{"id":221,"slug":"witsous","title":"Witsous – spesiaal vir Gert Smit","date":"2013-07-03T09:12:05","excerpt":"","categories":[33],"tags":[],"featured":null,"hasRecipe":false,"commentCount":4},{"id":219,"slug":"posttoastiepoeding","title":"Post toastie-poeding – Ai waars die dae in die koshuis","date":"2013-07-03T09:03:35","excerpt":"","categories":[5,8],"tags":[],"featured":null,"hasRecipe":false,"commentCount":0},{"id":215,"slug":"waatlemoenstukke","title":"Waatlemoenstukke – goue , goue juwele","date":"2013-07-02T21:27:59","excerpt":"","categories":[33,8],"tags":[336],"featured":null,"hasRecipe":false,"commentCount":8},{"id":196,"slug":"rysslaai","title":"Rysslaai – orige rys","date":"2013-07-02T16:38:15","excerpt":"","categories":[33,12],"tags":[],"featured":null,"hasRecipe":false,"commentCount":4},{"id":181,"slug":"rys","title":"Met Rys gaan jy ver","date":"2013-07-01T14:55:31","excerpt":"","categories":[321],"tags":[21],"featured":null,"hasRecipe":false,"commentCount":10},{"id":164,"slug":"rum-en-raisin-koek","title":"Rum en Raisin-koek","date":"2013-06-30T17:42:41","excerpt":"","categories":[5,316],"tags":[],"featured":null,"hasRecipe":false,"commentCount":2},{"id":161,"slug":"mango-en-jogurt-lekkerte","title":"Mango en jogurt lekkerte","date":"2013-06-29T16:51:00","excerpt":"","categories":[8],"tags":[],"featured":null,"hasRecipe":false,"commentCount":2},{"id":155,"slug":"sjokoladepoeding","title":"Warm dekadente sjokolade poeding – 6 porsies","date":"2013-06-25T14:52:02","excerpt":"","categories":[8],"tags":[],"featured":null,"hasRecipe":false,"commentCount":7},{"id":147,"slug":"krummelpap","title":"Krummelpap – maak jou lekker vol","date":"2013-06-25T13:52:48","excerpt":"","categories":[332],"tags":[],"featured":null,"hasRecipe":false,"commentCount":3},{"id":142,"slug":"flapjacks","title":"Flapjacks – weet nie wat dit in afrikaans is nie  20 flapjacks","date":"2013-06-25T12:17:52","excerpt":"","categories":[5],"tags":[],"featured":null,"hasRecipe":false,"commentCount":4},{"id":141,"slug":"frittata","title":"Vinnige eierpannekoek – frittata – 6 porsies","date":"2013-06-25T12:06:40","excerpt":"","categories":[332],"tags":[],"featured":null,"hasRecipe":false,"commentCount":13},{"id":139,"slug":"ham-en-eier-mooigeit","title":"Ham en eier mooigeit","date":"2013-06-25T11:47:07","excerpt":"","categories":[332],"tags":[],"featured":null,"hasRecipe":false,"commentCount":2},{"id":137,"slug":"pannekoek","title":"Pannekoek","date":"2013-04-03T11:46:52","excerpt":"","categories":[8],"tags":[333],"featured":null,"hasRecipe":false,"commentCount":4},{"id":136,"slug":"goue-eiers","title":"Goue eiers","date":"2013-04-03T10:26:04","excerpt":"","categories":[332],"tags":[218],"featured":null,"hasRecipe":false,"commentCount":1},{"id":132,"slug":"viskoekies","title":"Viskoekies","date":"2013-04-01T12:22:47","excerpt":"","categories":[30],"tags":[],"featured":null,"hasRecipe":false,"commentCount":11},{"id":104,"slug":"mates","title":"Mates","date":"2013-04-01T12:06:07","excerpt":"","categories":[2],"tags":[],"featured":null,"hasRecipe":false,"commentCount":12}]
