{
 "id": 1818,
 "slug": "banting-patats-soet-en-lekker",
 "title": "Banting patats – soet en lekker",
 "date": "2014-10-07T18:21:21",
 "modified": "2022-02-13T15:12:36",
 "excerpt": "Kyk die somer le voor en almal probeer maar daardie ekstra rolletjie afskud. Maar die lus vir n lekker soetpatat wil my nie afskud nie. Toe maak ek maar banting patats. BENODIG; 2 groot patats 30 ml coconut oil 60 ml botter 5 ml heuning 30 ml stevia suiker …",
 "categories": [
  33,
  6
 ],
 "tags": [
  350,
  264
 ],
 "featured": {
  "alt": "Banting patats – soet en lekker",
  "card": {
   "src": "/media/uploads/2017/10/featured-patat-1.jpg",
   "width": null,
   "height": null
  },
  "portrait": {
   "src": "/media/uploads/2017/10/featured-patat-1.jpg",
   "width": null,
   "height": null
  },
  "thumb": {
   "src": "/media/uploads/2017/10/featured-patat-1-150x150.jpg",
   "width": 150,
   "height": 150
  }
 },
 "commentStatus": "open",
 "seo": {
  "title": "Banting patats - soet en lekker - Marinda Kook",
  "description": null
 },
 "html": "<p>Kyk die somer le voor en almal probeer maar daardie ekstra rolletjie afskud.  Maar die lus vir n lekker soetpatat wil my nie afskud nie.  Toe maak ek maar banting patats.<a href=\"/media/uploads/2017/10/patat-3.jpg\"><img loading=\"lazy\" class=\"aligncenter size-large wp-image-1819\" alt=\"patat 3\" src=\"/media/uploads/2017/10/patat-3.jpg\" width=\"1024\" height=\"575\"></a></p>\n<p>&nbsp;</p>\n<p>BENODIG;</p>\n<ul>\n<li>2 groot patats</li>\n<li>30 ml coconut oil</li>\n<li>60 ml botter</li>\n<li>5 ml heuning</li>\n<li>30 ml stevia suiker of enige versoeter</li>\n<li>2 kaneelstokkies</li>\n<li>n knippie sout</li>\n</ul>\n<p>NOU:</p>\n<ol>\n<li>skil die patats en sny in ringetjies</li>\n<li>gooi die res van die bestandele in n pot en roer tot botter gesmelt is</li>\n<li>sit die patat in die pot en stel die plaat baie laag</li>\n<li>laat dit saggies kook sonder deksel</li>\n<li>probeer om die pot te skud in plaas daarvan om die patats te roer met n lepel  &#8211; dit breek maklik</li>\n<li>laat dit stadig prut totdat dit karamaliseer en die patat sag is.</li>\n</ol>\n<p>Heerlik, heerlik, heerlik!!!!!!!!<a href=\"/media/uploads/2017/10/patat-2.jpg\"><img loading=\"lazy\" class=\"aligncenter size-full wp-image-1820\" alt=\"patat 2\" src=\"/media/uploads/2017/10/patat-2.jpg\" width=\"305\" height=\"543\"></a></p>",
 "recipe": null,
 "comments": [
  {
   "id": 3272,
   "parent": 3265,
   "author": "marinda",
   "avatar": "https://secure.gravatar.com/avatar/f19140ecf5b531edcab42d7f2d07c2fc5516ea5d729fc89d2f660757c2880626?s=96&d=mm&r=g",
   "date": "2021-06-09T09:05:31",
   "html": "<p>Pesto?</p>"
  },
  {
   "id": 3271,
   "parent": 3266,
   "author": "marinda",
   "avatar": "https://secure.gravatar.com/avatar/f19140ecf5b531edcab42d7f2d07c2fc5516ea5d729fc89d2f660757c2880626?s=96&d=mm&r=g",
   "date": "2021-06-09T09:05:04",
   "html": "<p>Ria, praat jy van Maklik met Marinda?  Die een is uitverkoop.<br>\nMarinda se Koskas By Bargain Books. Exclusive Books.  Aanlyn by Takealot of Loot</p>"
  },
  {
   "id": 3266,
   "parent": 1603,
   "author": "Ria V DER schyff",
   "avatar": "https://secure.gravatar.com/avatar/9e6c79af7d06aad25a109d2e1e8e0e830edaa9e953f23c46fe05bcb7c60bce56?s=96&d=mm&r=g",
   "date": "2021-06-08T15:51:34",
   "html": "<p>Hallo marinda<br>\nDie anner kookboek<br>\nVoor jou nuuste 1<br>\nWaar Kan ek dit kry<br>\nDnki ria</p>"
  },
  {
   "id": 3265,
   "parent": 1603,
   "author": "Ria V DER schyff",
   "avatar": "https://secure.gravatar.com/avatar/9e6c79af7d06aad25a109d2e1e8e0e830edaa9e953f23c46fe05bcb7c60bce56?s=96&d=mm&r=g",
   "date": "2021-06-08T15:49:21",
   "html": "<p>Hallo<br>\nMarinda<br>\nHoop jys ok<br>\nEk weer weer jou program<br>\nGekyk<br>\nDie 1 waar jy gese het<br>\nJy mushrooms gevries<br>\nKnoffel gevries<br>\n Kook jy dit voor die tyd<br>\nPesto hoe maak jy dit<br>\nDnki ria</p>"
  },
  {
   "id": 3252,
   "parent": 3235,
   "author": "marinda",
   "avatar": "https://secure.gravatar.com/avatar/f19140ecf5b531edcab42d7f2d07c2fc5516ea5d729fc89d2f660757c2880626?s=96&d=mm&r=g",
   "date": "2021-05-31T16:46:17",
   "html": "<p>Jy maak my hart sing<br>\nMarinda</p>"
  },
  {
   "id": 3235,
   "parent": 0,
   "author": "Daleen Botes",
   "avatar": "https://secure.gravatar.com/avatar/d32c87776ba7e78ebe8ed1225d99fdbadbc90afcbacbc6a194cb4eb4928cafa7?s=96&d=mm&r=g",
   "date": "2021-05-24T18:31:13",
   "html": "<p>Vandag io die resep afgrkom en moet sê dis heerlik</p>"
  },
  {
   "id": 1603,
   "parent": 1534,
   "author": "marinda",
   "avatar": "https://secure.gravatar.com/avatar/f19140ecf5b531edcab42d7f2d07c2fc5516ea5d729fc89d2f660757c2880626?s=96&d=mm&r=g",
   "date": "2019-08-26T15:50:30",
   "html": "<p>Gaan vir ons enetjie uitwerk</p>"
  },
  {
   "id": 1534,
   "parent": 0,
   "author": "RIa Van der schyff",
   "avatar": "https://secure.gravatar.com/avatar/9e6c79af7d06aad25a109d2e1e8e0e830edaa9e953f23c46fe05bcb7c60bce56?s=96&d=mm&r=g",
   "date": "2019-07-17T13:20:19",
   "html": "<p>Marnda dnki pampoen poffertjies v banting asb</p>"
  },
  {
   "id": 545,
   "parent": 544,
   "author": "marindakook",
   "avatar": "https://secure.gravatar.com/avatar/ab5ec7ec84da837e94ee35ae002ddbc81d01b5dd02ce428686f2e5ca238faf18?s=96&d=mm&r=g",
   "date": "2014-10-09T08:23:18",
   "html": "<p>More Glenda</p>\n<p>Sal nog uitdink vir ons.  Ek maak vandag n banting bobotiebroodjie en sal dit later opsit.  Geniet die soetpatats.<br>\nGroete<br>\nMarinda</p>"
  },
  {
   "id": 544,
   "parent": 0,
   "author": "Glenda NIemand",
   "avatar": "https://secure.gravatar.com/avatar/2a8c4324d74e6ec71501676ad1dda352a80c4380673a37a32037d7b93b6aef04?s=96&d=mm&r=g",
   "date": "2014-10-09T08:00:13",
   "html": "<p>Ek gaan dit vir seker probeer Is daar nie nog resepte op die trant nie. Noem dit: Vir die soettand met &#8216;n &#8220;kinkel&#8221;</p>"
  }
 ]
}