{
 "id": 5289,
 "slug": "maklik-met-marinda-wicus-van-der-merwe",
 "title": "Maklik Met Marinda – Wicus van der Merwe",
 "date": "2018-12-20T17:23:23",
 "modified": "2022-02-13T15:34:19",
 "excerpt": "As ‘n man vir my vra vir ‘n garage pie en chips met gravy, dan weet ek hy het nie tyd en plek in sy lewe vir opgesmuk wees nie. Wicus van der Merwe is een van die opregste, galantste en eerbaarste mans wat ek in ‘n lang tyd ontmoet …",
 "categories": [
  36
 ],
 "tags": [
  55,
  103
 ],
 "featured": {
  "alt": "Maklik Met Marinda – Wicus van der Merwe",
  "card": {
   "src": "/media/uploads/2018/12/48020182_10155923344448365_6582753828909613056_o-1024x683.jpg",
   "width": 1024,
   "height": 683
  },
  "portrait": {
   "src": "/media/uploads/2018/12/48020182_10155923344448365_6582753828909613056_o-1024x683.jpg",
   "width": 1024,
   "height": 683
  },
  "thumb": {
   "src": "/media/uploads/2018/12/48020182_10155923344448365_6582753828909613056_o-150x150.jpg",
   "width": 150,
   "height": 150
  }
 },
 "commentStatus": "open",
 "seo": {
  "title": "Maklik Met Marinda - Wicus van der Merwe - Marinda Kook",
  "description": null
 },
 "html": "<p><iframe loading=\"lazy\" title=\"Maklik Met Marinda - S02E11 - Wicus van der Merwe\" width=\"800\" height=\"450\" src=\"https://www.youtube.com/embed/G2u2aUFXXLs?feature=oembed\" frameborder=\"0\" allow=\"accelerometer; autoplay; clipboard-write; encrypted-media; gyroscope; picture-in-picture\" allowfullscreen></iframe></p>\n<p>As &#8216;n man vir my vra vir &#8216;n garage pie en chips met gravy, dan weet ek hy het nie tyd en plek in sy lewe vir opgesmuk wees nie. Wicus van der Merwe is een van die opregste, galantste en eerbaarste mans wat ek in &#8216;n lang tyd ontmoet het. Sy opregtheid het sommer vroeg, vroeg in die keuse van sy gereg na vore gekom.</p>\n<p>Hy kom uit n familie met &#8216;n fyn sin vir humor. Dit het beslis op hom as kind &#8216;n inpak gemaak met &#8216;n pa soos Tolla van der Merwe. Ons het saam gekoes en gekook in die kombuis. Hy het wel vir my &#8216;n ligte hartaanval gegee toe hy my tannie noem, hy sê hy&#8217;s so grootgemaak dat as iemand ouer as hy is, noem jy haar tannie &#8211; dit het nie te goed by my afgegaan nie!</p>\n<p>Die kook saam met Wicus was een van die lekkerste dae in my kombuis. Ek salueer die talentvolle gentleman.</p>\n<p>Skakel Donderdag om 17:30 in op VIA, kanaal 147 vir hierdie spesiale episode.</p>",
 "recipe": null,
 "comments": []
}